Workbook

Sheet Deal ledger
O1: Row identity | Q1: Count | R1: Dates | W1: Price | AB1: Settlement | AD1: Conditions detail | AE1: Deadline & finality | AH1: Outcome | AK1: Source page | AL1: Related rows | AM1: Deal
A2: # | B2: When | C2: Who | D2: What happened | E2: Process | F2: Round | G2: Type | H2: Terms or outcome | I2: Formality | J2: Conditions level | K2: Why and evidence | L2: Source | M2: Review | N2: Reviewer note | O2: Row id | P2: Include | Q2: Count | R2: Date from | S2: Date to | T2: Working date | U2: Date basis | V2: Date method | W2: Price low | X2: Price high | Y2: Price kind | Z2: Price origin | AA2: Currency | AB2: All cash | AC2: Cash at closing | AD2: Conditions detail | AE2: Due date | AF2: Deadline treatment | AG2: Round finality | AH2: Decided by | AI2: Exit reason | AJ2: Outcome basis | AK2: Page | AL2: Related rows | AM2: Deal
A3: 1 | B3: Q4 2015 (calendar quarter) | C3: Party A (one of the Company’s Class I rail partners) | D3: Bidder interest | E3: 1 | F3: 0 | G3: Strategic | H3: Unpriced approach: Party A suggested possible joint venture arrangements and expressed interest in acquiring equity in the Company to develop strategic opportunities and enhance regional connectivity; scope as to control not specified (not treated as a whole-company bid); first sale-related contact, bidder-initiated, with the Chairman/CEO and the VP & Chief Commercial Officer; prompted the Board to form an investment-banker subcommittee. Count 1 = newly represented first-contact party (the contact fact is carried here; see Summary contact tally). | K3: Bidder interest (stated): the filing reports an unpriced expression of interest in acquiring equity, not a priced proposal, and no per-share or aggregate value exists for it. Direction: bidder-to-target. Quote: “In the fourth quarter of 2015, Robert H. Eder (the Company’s Chairman and Chief Executive Officer) and Frank K. Rogers (the Company’s Vice President and Chief Commercial Officer) met with one of the Company’s Class I rail partners (“Party A”) to discuss joint commercial opportunities. During the meeting, Party A suggested possible joint venture arrangements and expressed some interest in acquiring equity in the Company to further develop strategic opportunities and enhance regional connectivity” | L3: =HYPERLINK("#Source text!$D$2","P-001 (main: P-001)") | M3: Q5 | O3: R001 | P3: Yes | Q3: 1 | R3: 2015-10-01 | S3: 2015-12-31 | T3: 2015-11-15 | U3: Reported interval | V3: Assigned: midpoint | AK3: 27 | AM3: PWRR-G&W 2016
A4: 2 | B4: 01/27/2016 | C4: GHF (Greene Holcomb & Fisher LLC) — Company financial adviser; later BMO | D4: Adviser engaged | E4: 1 | F4: 0 | H4: Engaged as the Company’s investment banking firm: subcommittee recommendation approved at the 01/27/2016 executive session (Director Smith absent); GHF presented its qualifications and a proposed change-in-control process; represented it would not represent any potential buyer of the Company or any person proposing financing for such an offer; engagement followed the late-2015 banker interviews. GHF’s business was acquired by BMO Capital Markets Corp. on 08/01/2016 — the same adviser relationship continued as BMO (no second adviser row); aggregate fee ~$2.52 million. | K4: Adviser engaged (stated): engagement approval on the stated day; the engagement-letter date is not disclosed. The GHF-to-BMO acquisition is a firm change, not a new mandate (section 5.4). Quotes: “the subcommittee recommended to the Board that the Company retain GHF as its investment banking firm. At that meeting, representatives of GHF discussed with the Board its qualifications and a proposed process should the directors ultimately decide to proceed with a change in control transaction. As part of the interview process, GHF represented to the Company that it would not represent any potential buyer of the Company in connection with an offer to purchase the Company or any person proposing to provide financing in connection with such an offer. Following this presentation, the Board approved the subcommittee’s recommendation and the Company engaged GHF” / “GHF represented to the Company that it would not represent any potential buyer of the Company in connection with an offer to purchase the Company or any person proposing to provide financing in connection with such an offer” Fee: “the Company will pay BMO an aggregate fee of approximately $2.52 million”, the remainder and majority payable upon consummation (X-015). | L4: =HYPERLINK("#Source text!$D$2","P-001; X-015 (main: P-001)") | O4: R002 | P4: Yes | R4: 2016-01-27 | S4: 2016-01-27 | T4: 2016-01-27 | U4: Reported day | V4: Reported | AK4: 27 | AL4: mandate continued as BMO from 08/01/2016 (Summary advisers) | AM4: PWRR-G&W 2016
A5: 3 | B5: 03/14/2016 | C5: Board of Directors (special meeting) | D5: Target sale decision | E5: 1 | F5: 0 | H5: Decided to proceed with GHF’s proposed process: discussions with Party A plus solicitation of other third parties regarding a change in control transaction; qualified as an exploratory strategy, not a commitment to sell; appointed the Transaction Committee (Barrett (Chair), Anderson, Garvey) to supervise the process and recommend to the full Board; the Committee could not itself approve a change of control. | K5: Target sale decision (stated): “Representatives of GHF then proposed a process pursuant to which the Company would proceed with discussions with Party A and also solicit interest from other potential third parties regarding a change in control transaction” The qualification (exploratory strategy) is preserved. Committee appointment: “the Board appointed a special committee of independent directors of the Board (which we refer to as the “Transaction Committee”), composed of Frank W. Barrett (Chair), Richard W. Anderson and James C. Garvey, for the purpose of assisting in the supervision and oversight of the process on the full Board’s behalf and making a recommendation to the full Board” | L5: =HYPERLINK("#Source text!$D$3","P-002 (main: P-002)") | M5: Q1 | O5: R003 | P5: Yes | R5: 2016-03-14 | S5: 2016-03-14 | T5: 2016-03-14 | U5: Reported day | V5: Reported | AK5: 27 | AL5: candidate R1 anchor (rejected); R005 | AM5: PWRR-G&W 2016
A6: 4 | B6: 03/22/2016–03/23/2016 | C6: Party A | D6: Contact | E6: 1 | F6: 0 | G6: Strategic | H6: Management (CFO/Treasurer Noreck and other senior managers) met Party A representatives and informed Party A of GHF’s engagement. Repeat contact: Party A was already in contact from Q4 2015, so Count 0 (no double counting). | K6: Contact (stated), repeat within the process. Quotes: “On March 22, 2016 and March 23, 2016, Daniel T. Noreck (the Company’s Chief Financial Officer and Treasurer) and other members of the senior management team of the Company met with various representatives of Party A” / “met with various representatives of Party A on March 22 and 23, 2016 and had informed Party A of GHF’s engagement” A two-day series of meetings takes its first day as the Working date. | L6: =HYPERLINK("#Source text!$D$4","P-003; P-004 (main: P-003)") | O6: R004 | P6: Yes | Q6: 0 | R6: 2016-03-22 | S6: 2016-03-23 | T6: 2016-03-22 | U6: Reported interval | V6: Assigned: bound | AK6: 28 | AL6: first contact R001 | AM6: PWRR-G&W 2016
A7: 5 | B7: 03/24/2016 | C7: Transaction Committee | D7: Target decision | E7: 1 | F7: 0 | H7: Authorized GHF to contact Party A and other potential buyers to determine their interest in a change in control transaction. Candidate anchor for Round 1, rejected: an authorization to approach firms is not the completed outreach (the actual first wave is R007). | K7: Target decision (stated): “The Transaction Committee authorized GHF to contact Party A as well as other potential buyers to determine their level of interest in a change in control transaction” Kept as a rejected R1 anchor row so the boundary can be moved. | L7: =HYPERLINK("#Source text!$D$5","P-004 (main: P-004)") | M7: Q1 | O7: R005 | P7: Yes | R7: 2016-03-24 | S7: 2016-03-24 | T7: 2016-03-24 | U7: Reported day | V7: Reported | AK7: 28 | AL7: candidate R1 anchor (rejected); R007; R008 | AM7: PWRR-G&W 2016
A8: 6 | B8: 03/24/2016 | C8: Hinckley, Allen & Snyder LLP (Hinckley Allen) — Company legal counsel | D8: Adviser service observed | E8: 1 | F8: 0 | H8: Company legal counsel; participated in all Transaction Committee meetings; engagement date not disclosed; first shown acting 03/24/2016. | K8: Adviser service observed (stated): the filing shows Hinckley Allen already providing services on 03/24/2016; no selection or engagement date is disclosed, so the Working date is the earliest date shown acting. Quote: “representatives of each of GHF and the Company’s legal counsel, Hinckley, Allen & Snyder LLP (which we refer to as “Hinckley Allen”), participated in all meetings of the Transaction Committee” | L8: =HYPERLINK("#Source text!$D$5","P-004 (main: P-004)") | O8: R006 | P8: Yes | R8: 2016-03-24 | S8: 2016-03-24 | T8: 2016-03-24 | U8: Reported day | V8: Reported | AK8: 28 | AM8: PWRR-G&W 2016
A9: 7 | B9: week of 03/28/2016 | C9: 29 potential buyers (11 strategic incl. Party A; 18 financial) | D9: Contact | E9: 1 | F9: 1 | G9: Unknown | H9: First outreach wave: GHF contacted 11 potential strategic buyers (including Party A) and 18 potential financial buyers in accordance with the Transaction Committee’s directives; Count 29 = disclosed cohort size (includes Party A, already in contact since Q4 2015). Type: Unknown — the cohort mixes strategic and financial buyers (split supplied only for the signing wave, R009–R011). | K9: Contact (stated cohort, executed outreach). Quote: “During the week of March 28, 2016, in accordance with the Transaction Committee’s directives, representatives of GHF contacted 11 potential strategic buyers (including Party A) and 18 potential financial buyers” This is the R1 anchor event (see R008). | L9: =HYPERLINK("#Source text!$D$5","P-004 (main: P-004)") | M9: Q1 | O9: R007 | P9: Yes | Q9: 29 | R9: 2016-03-28 | S9: 2016-04-03 | T9: 2016-03-28 | U9: Reported interval | V9: Assigned: bound | AK9: 28 | AL9: R008 (anchor event) | AM9: PWRR-G&W 2016
A10: 8 | B10: week of 03/28/2016 | C10: Process (Round 1) | D10: Round opened | E10: 1 | F10: 1 | H10: R1 anchor: first outreach wave — GHF contacted 11 potential strategic buyers (including Party A) and 18 potential financial buyers (R007); candidate anchors: R003 (03/14/2016 sale-strategy decision), R005 (03/24/2016 authorization to contact). Objective: solicit change-in-control interest and confirm the continuing interest of NDA signers; the round runs through the IOI stage to the 06/01/2016 advancement decision. Round finality: Not final — no final/binding/best-and-final announcement and no move to definitive negotiation; the stage closed by selection to management presentations (R021). | K10: Round opened (convention/analytical). First outreach wave chosen under section 6.3(1); R003 and R005 are the retained rejected candidate anchors. Quote: “During the week of March 28, 2016, in accordance with the Transaction Committee’s directives, representatives of GHF contacted 11 potential strategic buyers (including Party A) and 18 potential financial buyers” | L10: =HYPERLINK("#Source text!$D$5","P-004 (main: P-004)") | M10: Q1 | O10: R008 | P10: Yes | R10: 2016-03-28 | S10: 2016-04-03 | T10: 2016-03-28 | U10: Reported interval | V10: Assigned: bound | AG10: Not final | AK10: 28 | AL10: anchor R007; candidates R003, R005 | AM10: PWRR-G&W 2016
A11: 9 | B11: from the week of 03/28/2016; by 04/22/2016 | C11: 10 remaining potential strategic buyers (11 contacted less G&W) | D11: NDA signed | E11: 1 | F11: 1 | G11: Strategic | H11: Confidentiality agreements signed by the potential strategic buyers of the outreach wave less G&W (recorded individually at R011); the agreements contained no “standstill” or similar provision prohibiting a proposal or offer; the wave’s memorandum was later distributed to signers including Party A, Party B and G&W. | K11: NDA signed (stated cohort; residual after G&W’s individual row, section 5.2). Base: “Each of the potential strategic buyers and 14 potential financial buyers subsequently executed confidentiality agreements” / “did not contain any “standstill” or similar provision that would prohibit a potential buyer from submitting a proposal or making an offer to acquire the Company” The signing wave spans the reported period, so the Working date takes its first day; the memorandum distribution bounds the signings: “the Company prepared a memorandum concerning the Company and its prospects, which was distributed to the potential buyers, including Party A, Party B and G&W, that had executed confidentiality agreements” (P-007). | L11: =HYPERLINK("#Source text!$D$5","P-004; P-007 (main: P-004)") | M11: Q3; Q7 | O11: R009 | P11: Yes | Q11: 10 | R11: 2016-03-28 | S11: 2016-04-22 | T11: 2016-03-28 | U11: Relative only | V11: Assigned: bound | AK11: 28 | AL11: R011 (G&W); R010 (financial residual) | AM11: PWRR-G&W 2016
A12: 10 | B12: from the week of 03/28/2016; by 04/22/2016 | C12: 14 potential financial buyers (of 18 contacted) | D12: NDA signed | E12: 1 | F12: 1 | G12: Financial | H12: Confidentiality agreements signed by 14 of the 18 potential financial buyers contacted in the outreach wave; same no-standstill terms and memorandum distribution. | K12: NDA signed (stated cohort). Quotes: “Each of the potential strategic buyers and 14 potential financial buyers subsequently executed confidentiality agreements” / “did not contain any “standstill” or similar provision that would prohibit a potential buyer from submitting a proposal or making an offer to acquire the Company” Memorandum distribution: “the Company prepared a memorandum concerning the Company and its prospects, which was distributed to the potential buyers, including Party A, Party B and G&W, that had executed confidentiality agreements” (P-007) bounds the signings. | L12: =HYPERLINK("#Source text!$D$5","P-004; P-007 (main: P-004)") | M12: Q3; Q7 | O12: R010 | P12: Yes | Q12: 14 | R12: 2016-03-28 | S12: 2016-04-22 | T12: 2016-03-28 | U12: Relative only | V12: Assigned: bound | AK12: 28 | AL12: R009 (strategic residual) | AM12: PWRR-G&W 2016
A13: 11 | B13: 04/03/2016 | C13: G&W (Genesee & Wyoming Inc.) | D13: NDA signed | E13: 1 | F13: 1 | G13: Strategic | H13: Acquisition-related confidentiality agreement between the Company and G&W dated 04/03/2016 (the merger agreement’s defined “Confidentiality Agreement”); G&W also met management at the 2016 Connections Convention (04/03–04/06) and received the memorandum. | K13: NDA signed (stated): the merger agreement definition fixes G&W’s individual date and the wave cohort rows (R009–R010) exclude it. Quotes: “shall mean the Confidentiality Agreement between the Company and Parent dated April 3, 2016” / “including Party A, Party B and G&W, that had executed confidentiality agreements” | L13: =HYPERLINK("#Source text!$D$31","X-001; P-007 (main: X-001)") | M13: Q3 | O13: R011 | P13: Yes | Q13: 1 | R13: 2016-04-03 | S13: 2016-04-03 | T13: 2016-04-03 | U13: Reported day | V13: Reported | AK13: A-48 | AL13: R009/R010 (wave cohorts) | AM13: PWRR-G&W 2016
A14: 12 | B14: 04/03/2016–04/06/2016 | C14: Five unnamed potential strategic buyers (incl. G&W) | D14: Information access changed | E14: 1 | F14: 1 | G14: Strategic | H14: GHF and Company management held a series of introductory management meetings with five potential strategic buyers (incl. G&W) at the American Short Line and Regional Railroad Association’s 2016 Connections Convention; the 14 financial-signer bidders and other NDA signers received no comparable management meetings at that time; the meetings were venue-based (no selection reason stated for the five). Count blank (access row). | K14: Information access changed (classification): management meetings given to some live bidders and not others, recorded once for the access decision (not per meeting). Quote: “held a series of introductory meetings with five potential strategic buyers (including G&W) at the American Short Line and Regional Railroad Association’s 2016 Connections Convention” | L14: =HYPERLINK("#Source text!$D$6","P-005 (main: P-005)") | M14: Q1 | O14: R012 | P14: Yes | R14: 2016-04-03 | S14: 2016-04-06 | T14: 2016-04-03 | U14: Reported interval | V14: Assigned: bound | AK14: 28 | AM14: PWRR-G&W 2016
A15: 13 | B15: 04/07/2016 | C15: Transaction Committee | D15: Target decision | E15: 1 | F15: 1 | H15: Authorized GHF to contact the five convention parties, other potential strategic buyers (including certain Class I railroads) and private equity firms under NDA to confirm their continuing interest. | K15: Target decision (stated). Quote: “the Transaction Committee authorized representatives of GHF, on behalf of the Company, to contact each of the five interested parties with whom management had met at the 2016 Connections Convention, as well as other potential strategic buyers (including certain Class I railroads) and private equity firms who had entered into confidentiality agreements with the Company to confirm their continuing interest” | L15: =HYPERLINK("#Source text!$D$7","P-006 (main: P-006)") | O15: R013 | P15: Yes | R15: 2016-04-07 | S15: 2016-04-07 | T15: 2016-04-07 | U15: Reported day | V15: Reported | AK15: 28 | AM15: PWRR-G&W 2016
A16: 14 | B16: by 04/07/2016; day not disclosed | C16: Two unnamed additional Class I railroads | D16: Contact | E16: 1 | F16: 1 | G16: Strategic | H16: Approached by the Company (management) before the 04/07/2016 committee report to gauge interest in a possible transaction; no NDA, bid or further participation reported; they never entered the process (no outcome row). Count 2 = cohort size. | K16: Contact (stated): “Mr. Noreck reported that the Company had also approached two additional Class I railroads to determine their interest in a possible transaction” Direction: target-to-bidder; the approach precedes the 04/07/2016 meeting (day not disclosed), so the bound is the report date. | L16: =HYPERLINK("#Source text!$D$7","P-006 (main: P-006)") | O16: R014 | P16: Yes | Q16: 2 | S16: 2016-04-07 | T16: 2016-04-07 | U16: Relative only | V16: Assigned: bound | AK16: 28 | AM16: PWRR-G&W 2016
A17: 15 | B17: 04/21/2016 | C17: Party B | D17: Contact | E17: 1 | F17: 1 | G17: Strategic | H17: Introductory meeting held by the Company and GHF with Party B; first individually recorded meeting for Party B. Repeat contact: Party B is treated as one of the contacted NDA signers of the March wave (R007/R009), so Count 0; the alternative reading is flagged in Q5. | K17: Contact (stated), repeat within the wave. Quote: “Subsequently, on April 21, 2016, the Company and representatives of GHF held an introductory meeting with another potential strategic buyer” | L17: =HYPERLINK("#Source text!$D$7","P-006 (main: P-006)") | M17: Q5 | O17: R015 | P17: Yes | Q17: 0 | R17: 2016-04-21 | S17: 2016-04-21 | T17: 2016-04-21 | U17: Reported day | V17: Reported | AK17: 28 | AM17: PWRR-G&W 2016
A18: 16 | B18: by 04/27/2016; IOI deadline 05/10/2016 | C18: Process (all potential buyers) | D18: Deadline set | E18: 1 | F18: 1 | H18: Each potential buyer advised to submit a non-binding indication of interest by 05/10/2016; the advice is reported at the 04/27/2016 executive session of the Board; deadline version 1 (later revised, R017). Communication day not disclosed. | K18: Deadline set (stated); known only by the 04/27/2016 report. Quote: “each potential buyer had been advised to submit a non-binding indication of interest by May 10, 2016” This date was superseded before arrival, so it stays in the set/revised history with no milestone row. | L18: =HYPERLINK("#Source text!$D$8","P-007 (main: P-007)") | M18: Q2 | O18: R016 | P18: Yes | S18: 2016-04-27 | T18: 2016-04-27 | U18: Relative only | V18: Assigned: bound | AE18: 2016-05-10 | AK18: 29 | AM18: PWRR-G&W 2016
A19: 17 | B19: after 04/27/2016; day not disclosed (new deadline 05/19/2016) | C19: Process (all potential buyers) | D19: Deadline revised | E19: 1 | F19: 1 | H19: IOI deadline postponed from 05/10/2016 to 05/19/2016 to ensure potential buyers had sufficient time to formulate their most compelling offers; requester not disclosed; all potential buyers affected. Treatment: Extended — this row moved the 05/10/2016 due date (recorded here and in the Summary map). | K19: Deadline revised (stated). Quote: “which deadline was subsequently postponed to May 19, 2016 to ensure the potential buyers had sufficient time to formulate their most compelling offers” Revision day not disclosed; window 04/27–05/19 bounded by the 04/27 report and the new due date; midpoint assigned. | L19: =HYPERLINK("#Source text!$D$8","P-007 (main: P-007)") | M19: Q2; Q7 | O19: R017 | P19: Yes | R19: 2016-04-27 | S19: 2016-05-19 | T19: 2016-05-08 | U19: Relative only | V19: Assigned: midpoint | AE19: 2016-05-19 | AF19: Extended | AK19: 29 | AL19: moves R016 (05/10) to 05/19 | AM19: PWRR-G&W 2016
A20: 18 | B20: 05/19/2016 | C20: Process (all potential buyers) | D20: Deadline | E20: 1 | F20: 1 | H20: IOI deadline reached while operative; nine IOIs were received between 05/19 and 06/01 (a window that straddles the due date, so no submission is treated as late) and the committee took its next step on the bids in hand (05/23 and 06/01 reviews; exclusions and advancement). Treatment: Enforced. | K20: Deadline (stated milestone; treatment convention). Quotes: “Between May 19, 2016 and June 1, 2016, the Company received nine written indications of interest” / “the Transaction Committee concluded that the two low bidders should be excluded from that process. The Transaction Committee authorized representatives of GHF to schedule in-person management presentations with the remaining seven potential buyers” | L20: =HYPERLINK("#Source text!$D$9","P-008 (main: P-008)") | M20: Q2 | O20: R018 | P20: Yes | R20: 2016-05-19 | S20: 2016-05-19 | T20: 2016-05-19 | U20: Reported day | V20: Reported | AE20: 2016-05-19 | AF20: Enforced | AK20: 29 | AM20: PWRR-G&W 2016
A21: 19 | B21: 05/19/2016–06/01/2016 | C21: Nine IOI submitters (anonymous cohort) | D21: Bid | E21: 1 | F21: 1 | G21: Unknown | H21: Nine written non-binding indications of interest at $17.93–$26.50 per share (as-converted; group envelope across the cohort, not any member’s price), implying equity values of $90–134 million; made before substantive diligence access (no data site before the 06/01/2016 advancement), so Heavy by context. Parties B, D, E, F and G&W and the two excluded low bidders fall within this cohort’s stage; Party C’s IOI came separately in Round 2 (R025). Type: Unknown — the cohort mixes strategic and financial bidders (split not supplied at this stage). | I21: Informal | J21: Heavy | K21: Bid (stated cohort; group-envelope convention, section 9.4). Quote: “Between May 19, 2016 and June 1, 2016, the Company received nine written indications of interest (“IOIs”) from potential buyers, with offer prices per share ranging from $17.93 to $26.50 (assuming the conversion of preferred stock into common stock), implying equity values of $90 million to $134 million” Formality: written non-binding indications; no returned agreement document or other formal signal at this stage → Informal. Conditions: preliminary non-binding indications made before substantive diligence access → Heavy by context. | L21: =HYPERLINK("#Source text!$D$9","P-008 (main: P-008)") | M21: Q6; Q7; Q8 | O21: R019 | P21: Yes | Q21: 9 | R21: 2016-05-19 | S21: 2016-06-01 | T21: 2016-05-19 | U21: Reported interval | V21: Assigned: deadline | W21: 17.93 | X21: 26.5 | Y21: Group envelope | Z21: Stated | AA21: USD | AB21: Not stated | AD21: Fin: not stated; DD required: not stated; DD open: no; Excl: not stated | AK21: 29 | AM21: PWRR-G&W 2016
A22: 20 | B22: by 05/19/2016 | C22: 16 remaining NDA signers (of the 25) | D22: Did not submit | E22: 1 | F22: 1 | G22: Unknown | H22: Inferred: residual — 25 NDA signers (11 strategic + 14 financial) − 9 IOI submitters = 16 non-submitters at the 05/19/2016 IOI deadline. Includes the wave’s silent signers never individually mentioned again; Party A may also sit here (see R035). Type: Unknown — type split of the residual is not supplied. | K22: Inferred: residual (section 10.2). Base: “Each of the potential strategic buyers and 14 potential financial buyers subsequently executed confidentiality agreements” (25); accounted submitters: nine IOIs (R019). No other stated exits, and the next transition names the continuing seven as all within the nine. Supporting quote: “Between May 19, 2016 and June 1, 2016, the Company received nine written indications of interest”. | L22: =HYPERLINK("#Source text!$D$5","P-004; P-008 (main: P-004)") | M22: Q4 | O22: R020 | P22: Yes | Q22: 16 | S22: 2016-05-19 | T22: 2016-05-19 | U22: Relative only | V22: Assigned: deadline | AH22: Unknown | AI22: Not stated | AJ22: Inferred: residual | AK22: 28 | AL22: base R009–R011; covered submitters R019 | AM22: PWRR-G&W 2016
A23: 21 | B23: 06/01/2016 (decision concluded at the 06/01/2016 meeting; meetings also 05/23/2016) | C23: Transaction Committee | D23: Target decision | E23: 1 | F23: 1 | H23: Concluded that the two low bidders should be excluded from the management-presentation process and authorized in-person management presentations with the remaining seven potential buyers plus additional due diligence and access to an internet data site for legal and financial due diligence. | K23: Target decision (stated). Considered at the 05/23 and 06/01/2016 meetings; Working date = last meeting day (Assigned: decision day). Quotes: “In view of the substantial amount of management time that would be required for management presentations, the Transaction Committee concluded that the two low bidders should be excluded from that process. The Transaction Committee authorized representatives of GHF to schedule in-person management presentations with the remaining seven potential buyers and allow these parties to conduct additional due diligence” / “given access to an internet data site to conduct legal and financial due diligence” | L23: =HYPERLINK("#Source text!$D$9","P-008 (main: P-008)") | M23: Q1 | O23: R021 | P23: Yes | R23: 2016-05-23 | S23: 2016-06-01 | T23: 2016-06-01 | U23: Reported interval | V23: Assigned: decision day | AK23: 29 | AL23: exclusions R022; advancement covered here | AM23: PWRR-G&W 2016
A24: 22 | B24: 06/01/2016 (decision concluded; meetings 05/23 and 06/01/2016) | C24: Two unnamed low bidders (of the nine IOI submitters) | D24: Dropped by target | E24: 1 | F24: 1 | G24: Unknown | H24: Excluded from the management-presentation and data-site stage as the two lowest-priced IOIs; stage left: Round 1 advancement; their IOIs remain among the nine received. Decided by: Target; Exit reason: Lower offer than rivals. Type: Unknown — split not supplied. | K24: Dropped by target (stated): the target excludes participants that had entered the process. Quote: “the Transaction Committee concluded that the two low bidders should be excluded from that” Being the two lowest is the stated reason (Lower offer than rivals); no price comparison of individual bids is disclosed. | L24: =HYPERLINK("#Source text!$D$9","P-008 (main: P-008)") | M24: Q4 | O24: R022 | P24: Yes | Q24: 2 | R24: 2016-05-23 | S24: 2016-06-01 | T24: 2016-06-01 | U24: Reported interval | V24: Assigned: decision day | AH24: Target | AI24: Lower offer than rivals | AJ24: Stated | AK24: 29 | AL24: selection R021; stage R019 | AM24: PWRR-G&W 2016
A25: 23 | B25: mid-June 2016 | C25: Process (Round 2) | D25: Round opened | E25: 1 | F25: 2 | H25: LOI stage: GHF instructed all potential buyers to submit non-binding LOIs by 07/20/2016, together with mark-ups of the forms of merger agreement, disclosure letter and voting agreement (posted to the data site 06/29, 06/30 and 07/11/2016); valuation requested on the basis of 100% of the outstanding common on a dollar-per-share basis as-converted, or the financial terms of any non-cash proposal; management presentations and data-site diligence ran through June–July (status update 06/30/2016); the Due date is carried on this row. Round finality: Inferred final — no final-stage announcement, but the round closed when the target moved to confirmatory due diligence and definitive negotiation with selected bidders (07/27/2016). | K25: Round opened (analytical/convention): a distinct drafting-and-information stage linked to new offers (section 6.3). Alternative boundary 06/01/2016 (advancement) rejected because no updated offers were sought then (Q1). Quotes: “In mid-June 2016, at the direction of the Transaction Committee, representatives of GHF instructed all potential buyers to submit non-binding letters of intent (“LOIs”) by July 20, 2016, together with mark-ups of the forms of merger agreement, disclosure letter and voting agreement, which GHF indicated would be posted to the internet data site” / “Potential buyers were instructed to provide a valuation for the Company based on the purchase of 100% of the outstanding common stock on a dollar per share basis (assuming conversion of the preferred stock into common stock) or the financial terms of any non-cash proposal” | L25: =HYPERLINK("#Source text!$D$10","P-009 (main: P-009)") | M25: Q1 | O25: R023 | P25: Yes | R25: 2016-06-11 | S25: 2016-06-19 | T25: 2016-06-15 | U25: Approximate window | V25: Assigned: midpoint | AE25: 2016-07-20 | AG25: Inferred final | AK25: 29 | AL25: candidate boundary R021 (06/01, rejected) | AM25: PWRR-G&W 2016
A26: 24 | B26: early July 2016 | C26: Party C | D26: NDA signed | E26: 1 | F26: 2 | G26: Strategic | H26: Late-entrant strategic buyer that approached the Company’s management in early July 2016 and executed a confidentiality agreement before receiving the memorandum provided to the other potential buyers. | K26: NDA signed (stated): “In early July 2016, a potential strategic buyer that had not previously been part of the process” / “After executing a confidentiality agreement, Party C was provided the memorandum concerning the Company provided to the other potential buyers” Day not disclosed (early-July band); midpoint assigned. Note: the Board’s reasons state 25 confidentiality agreements in total (Q3 reconciliation). | L26: =HYPERLINK("#Source text!$D$12","P-011 (main: P-011)") | M26: Q3 | O26: R024 | P26: Yes | Q26: 1 | R26: 2016-07-01 | S26: 2016-07-10 | T26: 2016-07-05 | U26: Approximate window | V26: Assigned: midpoint | AK26: 29 | AL26: R025 (IOI); R026 (catch-up access) | AM26: PWRR-G&W 2016
A27: 25 | B27: 07/12/2016 | C27: Party C | D27: Bid | E27: 1 | F27: 2 | G27: Strategic | H27: IOI at $21.00 per share (as-converted), implying an equity value of $108 million; non-binding and made on the memorandum only (data-site access followed), so Heavy by context; first Party C bid in Round 2. | I27: Informal | J27: Heavy | K27: Bid (stated). Quote: “On July 12, 2016, Party C submitted an IOI with an offer price per share of $21.00 (implying an equity value of $108 million)” Formality: non-binding indication with no returned agreement document → Informal. Conditions: pre-substantive-diligence indication (memorandum only) → Heavy by context. | L27: =HYPERLINK("#Source text!$D$12","P-011 (main: P-011)") | M27: Q6 | O27: R025 | P27: Yes | Q27: 1 | R27: 2016-07-12 | S27: 2016-07-12 | T27: 2016-07-12 | U27: Reported day | V27: Reported | W27: 21 | X27: 21 | Y27: Point | Z27: Stated | AA27: USD | AB27: Not stated | AD27: Fin: not stated; DD required: not stated; DD open: no; Excl: not stated | AK27: 29 | AM27: PWRR-G&W 2016
A28: 26 | B28: 07/12/2016–07/14/2016 (memorandum earlier, early July) | C28: Party C | D28: Information access changed | E28: 1 | F28: 2 | G28: Strategic | H28: Late-entrant catch-up access: after its NDA Party C received the memorandum; after its 07/12/2016 IOI it was given access to the internet data site and a telephone management presentation (07/14/2016) while other buyers’ diligence was under way; no comparable catch-up accommodation for other late parties is disclosed. Count blank (access row). | K28: Information access changed (late entrant’s catch-up access, section 4), recorded once. Quote: “Subsequently, Party C was provided access to the internet data site and the Company’s management held a management presentation with Party C by telephone on July 14, 2016” | L28: =HYPERLINK("#Source text!$D$12","P-011 (main: P-011)") | M28: Q1 | O28: R026 | P28: Yes | R28: 2016-07-12 | S28: 2016-07-14 | T28: 2016-07-12 | U28: Reported interval | V28: Assigned: bound | AK28: 29 | AL28: R024 (NDA), R025 (IOI) | AM28: PWRR-G&W 2016
A29: 27 | B29: 07/20/2016 | C29: Process (all potential buyers) | D29: Deadline | E29: 1 | F29: 2 | H29: LOI deadline reached; six LOIs were received in late July 2016 (G&W’s dated 07/21/2016) and were considered without any revision of the due date. Treatment: Late bids accepted. | K29: Deadline (stated; treatment convention). Quotes: “In late July 2016, the Company received six LOIs with offer prices per share ranging from $19.20 to $24.00” / “G&W submitted an LOI on July 21, 2016 to acquire the Company for a price of $21.15 per share (subject to a three-week exclusive diligence period)” A bid dated after the 07/20/2016 due date was considered without a revision → Late bids accepted (not Enforced). | L29: =HYPERLINK("#Source text!$D$13","P-012; P-014 (main: P-012)") | M29: Q2 | O29: R027 | P29: Yes | R29: 2016-07-20 | S29: 2016-07-20 | T29: 2016-07-20 | U29: Reported day | V29: Reported | AE29: 2016-07-20 | AF29: Late bids accepted | AK29: 29 | AM29: PWRR-G&W 2016
A30: 28 | B30: late July 2016 | C30: Party B | D30: Bid | E30: 1 | F30: 2 | G30: Strategic | H30: LOI at $24.00 per share (as-converted; point), subject to an expedited diligence review; returned mark-ups of the merger agreement and voting agreement with the LOI; highest of the six LOIs; consideration form not stated. | I30: Formal | J30: Light | K30: Bid (stated). Quotes: “Party B submitted an LOI to acquire the Company for a price of $24.00 per share (subject to an expedited diligence review)” / “Party B, G&W and another bidder (“Party D”) also provided mark-ups of the draft merger agreement and voting agreement” Formality: bidder-returned agreement and voting-agreement markups (strong signal 1) → Formal. Conditions: expedited diligence and final documentation only, no Heavy trigger → Light. | L30: =HYPERLINK("#Source text!$D$13","P-012; P-013 (main: P-012)") | M30: Q6 | O30: R028 | P30: Yes | Q30: 1 | R30: 2016-07-20 | S30: 2016-07-31 | T30: 2016-07-20 | U30: Approximate window | V30: Assigned: deadline | W30: 24 | X30: 24 | Y30: Point | Z30: Stated | AA30: USD | AB30: Not stated | AD30: Fin: not stated; DD required: confirmatory; DD open: yes; Excl: not stated | AK30: 29 | AM30: PWRR-G&W 2016
A31: 29 | B31: late July 2016 | C31: Party E | D31: Bid | E31: 1 | F31: 2 | G31: Strategic | H31: LOI at $21.26 per share (as-converted; point), subject to a 60-day exclusivity period for due diligence and negotiation of definitive documentation; provided a summary of material issues and proposed changes to the merger agreement and voting agreement instead of mark-ups. | I31: Informal | J31: Heavy | K31: Bid (stated). Quotes: “Party E (a strategic buyer) submitted an LOI to acquire the Company for a price of $21.26 per share (subject to a 60-day exclusivity period for due diligence and negotiation of definitive documentation)” / “One bidder (“Party E”) provided a summary of material issues and proposed changes to the merger agreement and voting agreement with respect to those issues” Formality: an issues summary is not a returned agreement markup and no other formal signal is reported → Informal under the working default (borderline; Q6). Conditions: stated exclusive, multi-week diligence period → Heavy. | L31: =HYPERLINK("#Source text!$D$16","P-015; P-012 (main: P-015)") | M31: Q6 | O31: R029 | P31: Yes | Q31: 1 | R31: 2016-07-20 | S31: 2016-07-31 | T31: 2016-07-20 | U31: Approximate window | V31: Assigned: deadline | W31: 21.26 | X31: 21.26 | Y31: Point | Z31: Stated | AA31: USD | AB31: Not stated | AD31: Fin: not stated; DD required: substantive (60 days); DD open: yes; Excl: requested (60 days) | AK31: 30 | AM31: PWRR-G&W 2016
A32: 30 | B32: late July 2016 | C32: Party D | D32: Bid | E32: 1 | F32: 2 | G32: Financial | H32: LOI at $21.00 per share (as-converted; point), subject to a four-week diligence period; returned mark-ups of the merger agreement and voting agreement. | I32: Formal | J32: Heavy | K32: Bid (stated). Quotes: “Party D (a financial buyer) submitted an LOI to acquire the Company for a price of $21.00 per share (subject to a four-week diligence period)” / “Party B, G&W and another bidder (“Party D”) also provided mark-ups of the draft merger agreement and voting agreement” Formality: bidder-returned markups → Formal. Conditions: stated multi-week diligence period → Heavy. | L32: =HYPERLINK("#Source text!$D$17","P-016; P-012 (main: P-016)") | M32: Q6 | O32: R030 | P32: Yes | Q32: 1 | R32: 2016-07-20 | S32: 2016-07-31 | T32: 2016-07-20 | U32: Approximate window | V32: Assigned: deadline | W32: 21 | X32: 21 | Y32: Point | Z32: Stated | AA32: USD | AB32: Not stated | AD32: Fin: not stated; DD required: substantive (4 wks); DD open: yes; Excl: not stated | AK32: 30 | AM32: PWRR-G&W 2016
A33: 31 | B33: late July 2016 | C33: Party C | D33: Bid | E33: 1 | F33: 2 | G33: Strategic | H33: LOI at $19.30 per share (as-converted; point), subject to a 30-day diligence period; revises Party C’s 07/12/2016 IOI of $21.00 (R025). | I33: Informal | J33: Heavy | K33: Bid (stated), second Party C bid in Round 2, so Count 0 (section 7.2). Quote: “Party C submitted an LOI to acquire the Company for a price of $19.30 per share (subject to a 30-day diligence period)” Formality: no returned agreement document → Informal. Conditions: stated 30-day diligence period → Heavy. | L33: =HYPERLINK("#Source text!$D$18","P-017 (main: P-017)") | M33: Q6 | O33: R031 | P33: Yes | Q33: 0 | R33: 2016-07-20 | S33: 2016-07-31 | T33: 2016-07-20 | U33: Approximate window | V33: Assigned: deadline | W33: 19.3 | X33: 19.3 | Y33: Point | Z33: Stated | AA33: USD | AB33: Not stated | AD33: Fin: not stated; DD required: substantive (30 days); DD open: yes; Excl: not stated | AK33: 30 | AL33: revises R025 | AM33: PWRR-G&W 2016
A34: 32 | B34: late July 2016 | C34: Party F | D34: Bid | E34: 1 | F34: 2 | G34: Strategic | H34: LOI at $19.20 per share (as-converted; point), subject to a 30-day due diligence period; lowest of the six LOIs. | I34: Informal | J34: Heavy | K34: Bid (stated). Quote: “Party F (a strategic buyer) submitted an LOI to acquire the Company for a price of $19.20 per share (subject to a 30-day due diligence period)” Formality: no returned agreement document → Informal. Conditions: stated 30-day diligence period → Heavy. | L34: =HYPERLINK("#Source text!$D$19","P-018 (main: P-018)") | M34: Q6 | O34: R032 | P34: Yes | Q34: 1 | R34: 2016-07-20 | S34: 2016-07-31 | T34: 2016-07-20 | U34: Approximate window | V34: Assigned: deadline | W34: 19.2 | X34: 19.2 | Y34: Point | Z34: Stated | AA34: USD | AB34: Not stated | AD34: Fin: not stated; DD required: substantive (30 days); DD open: yes; Excl: not stated | AK34: 30 | AM34: PWRR-G&W 2016
A35: 33 | B35: by 07/20/2016 | C35: One unnamed strategic bidder (of the seven advancing) | D35: Did not submit | E35: 1 | F35: 2 | G35: Strategic | H35: Elected not to submit an LOI in the 07/20/2016 solicitation despite advancing to management presentations and data-site diligence; Decided by: Bidder; not necessarily a permanent withdrawal. Count 1 = the one unnamed strategic non-submitter. | K35: Did not submit (stated): “One strategic buyer and one financial buyer elected not to submit an LOI” The two non-submitters are the arithmetic remainder of the seven advancing bidders after the five of them that submitted LOIs; the six-LOI receipt is reported at “In late July 2016, the Company received six LOIs with offer prices per share ranging from $19.20 to $24.00” (P-012). | L35: =HYPERLINK("#Source text!$D$13","P-012; P-019 (main: P-012)") | M35: Q4 | O35: R033 | P35: Yes | Q35: 1 | S35: 2016-07-20 | T35: 2016-07-20 | U35: Relative only | V35: Assigned: deadline | AH35: Bidder | AI35: Not stated | AJ35: Stated | AK35: 29 | AM35: PWRR-G&W 2016
A36: 34 | B36: by 07/20/2016 | C36: One unnamed financial bidder (of the seven advancing) | D36: Did not submit | E36: 1 | F36: 2 | G36: Financial | H36: Elected not to submit an LOI in the 07/20/2016 solicitation despite advancing to management presentations and data-site diligence; Decided by: Bidder; not necessarily a permanent withdrawal. Count 1 = the one unnamed financial non-submitter. | K36: Did not submit (stated): “One strategic buyer and one financial buyer elected not to submit an LOI” The six-LOI receipt is reported at “In late July 2016, the Company received six LOIs with offer prices per share ranging from $19.20 to $24.00” (P-012). | L36: =HYPERLINK("#Source text!$D$13","P-012; P-019 (main: P-012)") | M36: Q4 | O36: R034 | P36: Yes | Q36: 1 | S36: 2016-07-20 | T36: 2016-07-20 | U36: Relative only | V36: Assigned: deadline | AH36: Bidder | AI36: Not stated | AJ36: Stated | AK36: 29 | AM36: PWRR-G&W 2016
A37: 35 | B37: by 07/20/2016 | C37: Party A (identity row) | D37: Did not submit | E37: 1 | F37: 2 | G37: Strategic | H37: Inferred: identity — Party A is not among the six named LOI submitters, the first continuing set the filing identifies by name; the row records only that Party A was out by this transition, not which anonymous exit was its own. Count 0. Covering cohorts that could already count it: R033 (unnamed strategic LOI non-submitter — recommended reading), R020 (16 residual non-submitters, which would place it at 05/19/2016), R022 (two low bidders). See Q4/Q5. No counts moved from a cohort to this name. | K37: Inferred: identity (section 10.2): Party A is introduced in Q4 2015, named among the memorandum recipients, and never mentioned again; the first named continuing set without it is the six LOI submitters: “In late July 2016, the Company received six LOIs with offer prices per share ranging from $19.20 to $24.00” (P-012). Other quotes: “including Party A, Party B and G&W, that had executed confidentiality agreements” / “proceed with confirmatory due diligence and negotiations with G&W and Party B because of the higher offers made by each of G&W and Party B relative to the other potential buyers” | L37: =HYPERLINK("#Source text!$D$8","P-007; P-012; P-020 (main: P-007)") | M37: Q4; Q5 | O37: R035 | P37: Yes | Q37: 0 | S37: 2016-07-20 | T37: 2016-07-20 | U37: Relative only | V37: Assigned: deadline | AH37: Unknown | AI37: Not stated | AJ37: Inferred: identity | AK37: 28 | AM37: PWRR-G&W 2016
A38: 36 | B38: 07/21/2016 | C38: G&W | D38: Bid | E38: 1 | F38: 2 | G38: Strategic | H38: LOI at $21.15 per share (as-converted; point) = $20.02 cash at closing plus a $1.13 contingent value right tied to the subsequent sale of the Company’s South Quay property (cash-settled CVR; payoff uncertain), subject to a three-week exclusive diligence period; also returned a mark-up of the disclosure letter; submitted one day after the 07/20/2016 due date. | I38: Formal | J38: Heavy | K38: Bid (stated; the payment split is preserved). Quotes: “G&W submitted an LOI on July 21, 2016 to acquire the Company for a price of $21.15 per share (subject to a three-week exclusive diligence period). The price included $20.02 cash at closing and $1.13 in the form of a contingent value right, the value of which was based on the subsequent sale of the Company’s South Quay property” / “G&W also provided a mark-up of the disclosure letter” Formality: returned transaction-document markup plus engagement with definitive terms → Formal. Conditions: stated three-week exclusive diligence period → Heavy. All cash: Yes (cash plus a contingent cash payment). | L38: =HYPERLINK("#Source text!$D$15","P-014 (main: P-014)") | M38: Q6; Q8 | O38: R036 | P38: Yes | Q38: 1 | R38: 2016-07-21 | S38: 2016-07-21 | T38: 2016-07-21 | U38: Reported day | V38: Reported | W38: 21.15 | X38: 21.15 | Y38: Point | Z38: Stated | AA38: USD | AB38: Yes | AC38: 20.02 | AD38: Fin: not stated; DD required: substantive (3 wks); DD open: yes; Excl: requested (3 wks) | AK38: 29 | AL38: revised by R037 | AM38: PWRR-G&W 2016
A39: 37 | B39: 07/26/2016 | C39: G&W | D39: Bid | E39: 1 | F39: 2 | G39: Strategic | H39: Revised LOI at $22.15 per share (as-converted; point) = $21.02 cash plus the unchanged $1.13 South Quay CVR, submitted after GHF feedback that its price and CVR structure were not competitive; second G&W bid in Round 2, so Count 0. | I39: Formal | J39: Heavy | K39: Bid (stated price revision; section 9.1 keeps revisions as Bid rows). Quote: “On July 26, 2016, in response to feedback from representatives of GHF indicating its price and CVR structure were not competitive, G&W submitted a revised LOI, which increased its offer to $22.15 per share” Conditions unchanged: three-week exclusive diligence period → Heavy. | L39: =HYPERLINK("#Source text!$D$15","P-014 (main: P-014)") | M39: Q6; Q8 | O39: R037 | P39: Yes | Q39: 0 | R39: 2016-07-26 | S39: 2016-07-26 | T39: 2016-07-26 | U39: Reported day | V39: Reported | W39: 22.15 | X39: 22.15 | Y39: Point | Z39: Stated | AA39: USD | AB39: Yes | AC39: 21.02 | AD39: Fin: not stated; DD required: substantive (3 wks); DD open: yes; Excl: requested (3 wks) | AK39: 29 | AL39: revises R036 | AM39: PWRR-G&W 2016
A40: 38 | B40: 07/27/2016 | C40: Transaction Committee (in person after the regular quarterly Board meeting) | D40: Target decision | E40: 1 | F40: 2 | H40: Concluded that the Company should proceed with confirmatory due diligence and negotiations with G&W and Party B because of their higher offers, and directed that the remaining bidders be told they were no longer involved; independent directors updated (Director Smith recused because GATX Corporation, which he serves and which holds 4.92% of the common stock, might be a potential buyer). | K40: Target decision (stated): selection of two finalists and exclusion of the rest in one shared decision. Quotes: “The Transaction Committee concluded that the Company should proceed with confirmatory due diligence and negotiations with G&W and Party B because of the higher offers made by each of G&W and Party B relative to the other potential buyers” / “representatives of GHF subsequently contacted the remaining bidders to inform them that they were no longer involved in the process” / “Director Smith is Vice President and Group Executive, Locomotive Group of GATX Corporation (“GATX”), which owns 4.92% of the Company’s common stock. In order to avoid any potential conflict, Mr. Smith elected to recuse himself from participating in this and other Board meetings at which the bidding process and any potential transaction were to be discussed because of the possibility that GATX might be a potential buyer of the Company” | L40: =HYPERLINK("#Source text!$D$21","P-020 (main: P-020)") | M40: Q1 | O40: R038 | P40: Yes | R40: 2016-07-27 | S40: 2016-07-27 | T40: 2016-07-27 | U40: Reported day | V40: Reported | AK40: 30 | AL40: closes R023; drops R039–R042; R043 | AM40: PWRR-G&W 2016
A41: 39 | B41: after 07/27/2016; day not disclosed | C41: Party C | D41: Dropped by target | E41: 1 | F41: 2 | G41: Strategic | H41: Told after the 07/27/2016 selection that it was no longer involved in the process; stage left: Round 2 (the selection stage); Decided by: Target; Exit reason: Lower offer than rivals (the higher offers of G&W and Party B). | K41: Dropped by target (stated as to the group; individual identification of the remaining bidders follows their LOI participation — all six LOI submitters except G&W and Party B). Quote: “representatives of GHF subsequently contacted the remaining bidders to inform them that they were no longer involved in the process” The notification is undated and follows the decision; assigned to the decision day. | L41: =HYPERLINK("#Source text!$D$21","P-020 (main: P-020)") | O41: R039 | P41: Yes | Q41: 1 | S41: 2016-07-27 | T41: 2016-07-27 | U41: Relative only | V41: Assigned: decision day | AH41: Target | AI41: Lower offer than rivals | AJ41: Stated | AK41: 30 | AL41: selection R038; earlier bid R031 | AM41: PWRR-G&W 2016
A42: 40 | B42: after 07/27/2016; day not disclosed | C42: Party D | D42: Dropped by target | E42: 1 | F42: 2 | G42: Financial | H42: Told after the 07/27/2016 selection that it was no longer involved in the process; stage left: Round 2 (the selection stage); Decided by: Target; Exit reason: Lower offer than rivals (the higher offers of G&W and Party B). | K42: Dropped by target (stated as to the group; individual identification of the remaining bidders follows their LOI participation — all six LOI submitters except G&W and Party B). Quote: “representatives of GHF subsequently contacted the remaining bidders to inform them that they were no longer involved in the process” The notification is undated and follows the decision; assigned to the decision day. | L42: =HYPERLINK("#Source text!$D$21","P-020 (main: P-020)") | O42: R040 | P42: Yes | Q42: 1 | S42: 2016-07-27 | T42: 2016-07-27 | U42: Relative only | V42: Assigned: decision day | AH42: Target | AI42: Lower offer than rivals | AJ42: Stated | AK42: 30 | AL42: selection R038; earlier bid R030 | AM42: PWRR-G&W 2016
A43: 41 | B43: after 07/27/2016; day not disclosed | C43: Party E | D43: Dropped by target | E43: 1 | F43: 2 | G43: Strategic | H43: Told after the 07/27/2016 selection that it was no longer involved in the process; stage left: Round 2 (the selection stage); Decided by: Target; Exit reason: Lower offer than rivals (the higher offers of G&W and Party B). | K43: Dropped by target (stated as to the group; individual identification of the remaining bidders follows their LOI participation — all six LOI submitters except G&W and Party B). Quote: “representatives of GHF subsequently contacted the remaining bidders to inform them that they were no longer involved in the process” The notification is undated and follows the decision; assigned to the decision day. | L43: =HYPERLINK("#Source text!$D$21","P-020 (main: P-020)") | O43: R041 | P43: Yes | Q43: 1 | S43: 2016-07-27 | T43: 2016-07-27 | U43: Relative only | V43: Assigned: decision day | AH43: Target | AI43: Lower offer than rivals | AJ43: Stated | AK43: 30 | AL43: selection R038; earlier bid R029 | AM43: PWRR-G&W 2016
A44: 42 | B44: after 07/27/2016; day not disclosed | C44: Party F | D44: Dropped by target | E44: 1 | F44: 2 | G44: Strategic | H44: Told after the 07/27/2016 selection that it was no longer involved in the process; stage left: Round 2 (the selection stage); Decided by: Target; Exit reason: Lower offer than rivals (the higher offers of G&W and Party B). | K44: Dropped by target (stated as to the group; individual identification of the remaining bidders follows their LOI participation — all six LOI submitters except G&W and Party B). Quote: “representatives of GHF subsequently contacted the remaining bidders to inform them that they were no longer involved in the process” The notification is undated and follows the decision; assigned to the decision day. | L44: =HYPERLINK("#Source text!$D$21","P-020 (main: P-020)") | O44: R042 | P44: Yes | Q44: 1 | S44: 2016-07-27 | T44: 2016-07-27 | U44: Relative only | V44: Assigned: decision day | AH44: Target | AI44: Lower offer than rivals | AJ44: Stated | AK44: 30 | AL44: selection R038; earlier bid R032 | AM44: PWRR-G&W 2016
A45: 43 | B45: 07/27/2016 | C45: Process (Round 3) | D45: Round opened | E45: 1 | F45: 3 | H45: Confirmatory due diligence and definitive negotiation with selected bidders (G&W and Party B): on-site financial, legal and environmental diligence including hi-rail track inspections (07/27–08/11/2016); revised merger agreement and voting agreement to Party B (08/01/2016) and G&W (08/03/2016); Party B prioritized from 08/04/2016. Round finality: Inferred final — the target moved to definitive negotiation with the selected bidders at this round’s opening and concluded with the executed 08/12/2016 agreement; no further solicitation. Alternative boundaries 08/04 and 08/12 rejected (Q1). | K45: Round opened (section 6.3: the target moves to definitive negotiation with selected bidders). Quotes: “proceed with confirmatory due diligence and negotiations with G&W and Party B because of the higher offers made by each of G&W and Party B” / “From July 27, 2016 through August 11, 2016, Party B and G&W conducted on-site financial, legal and environmental due diligence, including hi-rail trips to inspect the Company’s track infrastructure” | L45: =HYPERLINK("#Source text!$D$21","P-020; P-022 (main: P-020)") | M45: Q1 | O45: R043 | P45: Yes | R45: 2016-07-27 | S45: 2016-07-27 | T45: 2016-07-27 | U45: Reported day | V45: Reported | AG45: Inferred final | AK45: 30 | AL45: candidates 08/04/2016 and 08/12/2016 (rejected) | AM45: PWRR-G&W 2016
A46: 44 | B46: 07/29/2016 | C46: Party D | D46: Re-entered | E46: 1 | F46: 3 | G46: Financial | H46: Renewed participation after the 07/27/2016 exclusion: on a GHF call, Party D expressed interest in reengaging and enhancing its offer; a revised LOI followed on 08/01/2016 (R046). Decided by: Bidder; renewed activity, not a new NDA. Count 1. | K46: Re-entered (stated): renewed activity after a recorded departure (section 10.1). Quote: “On July 29, 2016, representatives of GHF had calls with Party D and Party E. During those calls, Party D and Party E both expressed interest in reengaging and enhancing their offers” | L46: =HYPERLINK("#Source text!$D$22","P-021 (main: P-021)") | M46: Q4 | O46: R044 | P46: Yes | Q46: 1 | R46: 2016-07-29 | S46: 2016-07-29 | T46: 2016-07-29 | U46: Reported day | V46: Reported | AH46: Bidder | AJ46: Stated | AK46: 30 | AL46: reopens after R040 | AM46: PWRR-G&W 2016
A47: 45 | B47: 07/29/2016 | C47: Party E | D47: Re-entered | E47: 1 | F47: 3 | G47: Strategic | H47: Renewed participation after the 07/27/2016 exclusion: on a GHF call, Party E expressed interest in reengaging and enhancing its offer; a revised LOI followed on 08/01/2016 (R047). Decided by: Bidder; renewed activity, not a new NDA. Count 1. | K47: Re-entered (stated): renewed activity after a recorded departure (section 10.1). Quote: “On July 29, 2016, representatives of GHF had calls with Party D and Party E. During those calls, Party D and Party E both expressed interest in reengaging and enhancing their offers” | L47: =HYPERLINK("#Source text!$D$22","P-021 (main: P-021)") | M47: Q4 | O47: R045 | P47: Yes | Q47: 1 | R47: 2016-07-29 | S47: 2016-07-29 | T47: 2016-07-29 | U47: Reported day | V47: Reported | AH47: Bidder | AJ47: Stated | AK47: 30 | AL47: reopens after R041 | AM47: PWRR-G&W 2016
A48: 46 | B48: 08/01/2016 | C48: Party D | D48: Bid | E48: 1 | F48: 3 | G48: Financial | H48: Revised LOI at $24.00 per share (as-converted; point) with a 30-day due diligence period (up from four weeks); on 08/02/2016 also requested that the Company commit not to enter an agreement with another bidder during that period (request declined). First Party D bid in Round 3 (Count 1). | I48: Formal | J48: Heavy | K48: Bid (stated price revision). Quotes: “On August 1, 2016, Party D submitted a revised LOI at a price of $24.00 per share” / “Both revised proposals contained a 30-day due diligence period” Exclusivity request: “Party D declined to shorten its due diligence period and requested that the Company commit that it would not enter into an agreement with another bidder during its 30-day due diligence period” Formality: carried forward from Party D’s returned mark-ups (one continuing proposal, section 9.2) → Formal. Conditions: stated 30-day diligence period and the later no-sign demand → Heavy. | L48: =HYPERLINK("#Source text!$D$22","P-021 (main: P-021)") | M48: Q6 | O48: R046 | P48: Yes | Q48: 1 | R48: 2016-08-01 | S48: 2016-08-01 | T48: 2016-08-01 | U48: Reported day | V48: Reported | W48: 24 | X48: 24 | Y48: Point | Z48: Stated | AA48: USD | AB48: Not stated | AD48: Fin: not stated; DD required: substantive (30 days); DD open: yes; Excl: requested (30 days) | AK48: 30 | AL48: revises R030; dropped R040, re-entered R044 | AM48: PWRR-G&W 2016
A49: 47 | B49: 08/01/2016 | C49: Party E | D49: Bid | E49: 1 | F49: 3 | G49: Strategic | H49: Support: Party F (financing) — revised LOI at $23.81 per share (as-converted; point) with a 30-day due diligence period, submitted along with financing support from Party F (which had exited on 07/27/2016; no re-entry row and no independent bid by Party F after its exit). First Party E bid in Round 3 (Count 1). | I49: Informal | J49: Heavy | K49: Bid (stated price revision with a disclosed financing-support relationship; section 5.3 records support on the supported bidder’s offer row). Quotes: “Party E submitted a revised LOI, along with financing support, from Party F, at a price of $23.81 per share” / “Both revised proposals contained a 30-day due diligence period” Formality: carries forward Party E’s Informal status (issues summary; no markup returned) — flagged Q6. Conditions: 30-day diligence period → Heavy. | L49: =HYPERLINK("#Source text!$D$22","P-021 (main: P-021)") | M49: Q6 | O49: R047 | P49: Yes | Q49: 1 | R49: 2016-08-01 | S49: 2016-08-01 | T49: 2016-08-01 | U49: Reported day | V49: Reported | W49: 23.81 | X49: 23.81 | Y49: Point | Z49: Stated | AA49: USD | AB49: Not stated | AD49: Fin: not stated; DD required: substantive (30 days); DD open: yes; Excl: not stated | AK49: 30 | AL49: revises R029; supporter exited at R042 (no re-entry); support ended with R048 | AM49: PWRR-G&W 2016
A50: 48 | B50: 08/02/2016 | C50: Party E | D50: Bid | E50: 1 | F50: 3 | G50: Strategic | H50: Reverted to its original proposal: withdrew the revised $23.81 LOI and confirmed the original proposal of $21.26 per share (the financing support for the withdrawn revised proposal ended); a bid reversion, not a process withdrawal; second Party E bid in Round 3, so Count 0. | I50: Informal | J50: Heavy | K50: Bid reversion (stated; section 9.1 keeps reversions as Bid rows). Quote: “confirmed its original proposal of $21.26 per share” Formality: Informal (as R029). Conditions: the original proposal’s 60-day exclusivity/diligence terms stand → Heavy. | L50: =HYPERLINK("#Source text!$D$22","P-021 (main: P-021)") | M50: Q6 | O50: R048 | P50: Yes | Q50: 0 | R50: 2016-08-02 | S50: 2016-08-02 | T50: 2016-08-02 | U50: Reported day | V50: Reported | W50: 21.26 | X50: 21.26 | Y50: Point | Z50: Stated | AA50: USD | AB50: Not stated | AD50: Fin: not stated; DD required: substantive (60 days); DD open: yes; Excl: requested (60 days) | AK50: 30 | AL50: reverts to R029; supersedes R047 | AM50: PWRR-G&W 2016
A51: 49 | B51: 08/02/2016 | C51: Party D | D51: Withdrew | E51: 1 | F51: 3 | G51: Financial | H51: Declined to shorten its 30-day due diligence period and requested a commitment that the Company not enter an agreement with another bidder during that period; in light of the active interest of Party B and G&W the Company declined to commit, at which point Party D indicated it would not proceed with further due diligence at that time. Decided by: Bidder; Exit reason: Terms or process. | K51: Withdrew (stated): the bidder communicates that it will not continue participating. Quote: “Party D declined to shorten its due diligence period and requested that the Company commit that it would not enter into an agreement with another bidder during its 30-day due diligence period. In light of the active interest of Party B and G&W, the Company declined to make such a commitment, at which point Party D indicated that it would not proceed with further due diligence at that time” The reason is terms/process (refused a shorter diligence period; the no-sign commitment was declined). | L51: =HYPERLINK("#Source text!$D$22","P-021 (main: P-021)") | M51: Q4 | O51: R049 | P51: Yes | Q51: 1 | R51: 2016-08-02 | S51: 2016-08-02 | T51: 2016-08-02 | U51: Reported day | V51: Reported | AH51: Bidder | AI51: Terms or process | AJ51: Stated | AK51: 30 | AL51: after revised LOI R046; dropped R040; re-entered R044 | AM51: PWRR-G&W 2016
A52: 50 | B52: 08/09/2016–08/11/2016 | C52: G&W | D52: Material process update | E52: 1 | F52: 3 | G52: Strategic | H52: Continued due diligence granted to G&W: after the 08/09/2016 decision directing BMO to tell G&W that the Company intended to enter a merger agreement with another bidder, G&W requested continued due diligence to potentially facilitate an improved offer; the request was granted and G&W completed physical diligence on 08/10–08/11/2016, then indicated a possible revised LOI for 08/12/2016. Precise action: access/continued diligence granted to a rival after the target’s selection of Party B. | K52: Material process update (stated): consequential development with no more specific label; it preceded G&W’s 08/12/2016 bid. Quotes: “G&W requested that it be allowed to continue its due diligence, including physical due diligence on August 10 and August 11, 2016, to potentially facilitate an improved offer, which request was granted” / “On August 11, 2016, G&W indicated its possible intention to submit a revised LOI on August 12, 2016, having just completed its physical diligence of the Company” | L52: =HYPERLINK("#Source text!$D$24","P-023 (main: P-023)") | M52: Q1 | O52: R050 | P52: Yes | R52: 2016-08-09 | S52: 2016-08-11 | T52: 2016-08-09 | U52: Reported interval | V52: Assigned: bound | AK52: 31 | AM52: PWRR-G&W 2016
A53: 51 | B53: 08/10/2016 | C53: Simpson Thacher & Bartlett LLP (Simpson Thacher) — G&W legal counsel | D53: Adviser service observed | E53: 1 | F53: 3 | H53: G&W’s legal counsel; first shown acting 08/10/2016 (discussed merger agreement and voting agreement provisions with Hinckley Allen and received a revised disclosure letter); engagement date not disclosed. | K53: Adviser service observed (stated): the filing shows Simpson Thacher acting; no engagement date. Quote: “representatives of Hinckley Allen and Simpson Thacher & Bartlett LLP (which we refer to as “Simpson Thacher”), G&W’s legal counsel” | L53: =HYPERLINK("#Source text!$D$24","P-023 (main: P-023)") | O53: R051 | P53: Yes | R53: 2016-08-10 | S53: 2016-08-10 | T53: 2016-08-10 | U53: Reported day | V53: Reported | AK53: 31 | AM53: PWRR-G&W 2016
A54: 52 | B54: 08/12/2016 (morning) | C54: G&W | D54: Bid | E54: 1 | F54: 3 | G54: Strategic | H54: Revised LOI at $25.00 per share in cash (as-converted; point), dropping the previously proposed CVR, together with mark-ups of the merger agreement and voting agreement; offer stated to expire 6:00 p.m. on 08/13/2016; submitted after G&W completed physical diligence and after the Company told G&W it intended to sign with another bidder; first G&W bid in Round 3 (Count 1). | I54: Formal | J54: Light | K54: Bid (stated final price revision). Quote: “G&W submitted a revised LOI to acquire the Company for a price of $25.00 per share in cash, which excluded the previously proposed CVR, together with mark-ups of the merger agreement and the voting agreement. G&W’s LOI further indicated that the offer would expire at 6:00 p.m. on the following” Formality: returned agreement and voting-agreement markups plus a price confirmation in definitive negotiation → Formal. Conditions: diligence completed 08/11/2016, no diligence or exclusivity condition attached, no Heavy trigger reported → Light (financing silent; silence does not raise or lower the level, and None is not claimed because financing is not stated). All cash: Yes; cash at closing $25.00. | L54: =HYPERLINK("#Source text!$D$25","P-024 (main: P-024)") | M54: Q6; Q8 | O54: R052 | P54: Yes | Q54: 1 | R54: 2016-08-12 | S54: 2016-08-12 | T54: 2016-08-12 | U54: Reported day | V54: Reported | W54: 25 | X54: 25 | Y54: Point | Z54: Stated | AA54: USD | AB54: Yes | AC54: 25 | AD54: Fin: not stated; DD required: none; DD open: no; Excl: none | AK54: 31 | AL54: revises R037 | AM54: PWRR-G&W 2016
A55: 53 | B55: 08/12/2016 (afternoon; Transaction Committee met 10:30 a.m.) | C55: Board of Directors (special meeting; Director Smith recused) | D55: Target decision | E55: 1 | F55: 3 | H55: After the Committee’s 10:30 a.m. meeting (BMO directed to inform Party B that a higher revised LOI had been received) and the Board’s comparison of the two drafts (G&W $1.00 per share higher; lower termination fee; STB approval timing not materially different; no financing condition), the Board asked BMO to seek a higher price from Party B — Party B declined; the Board determined G&W’s offer a superior proposal, received BMO’s oral fairness opinion (written opinion dated 08/12/2016, to holders other than the Eder Trusts) and approved the merger agreement and recommended shareholder approval. | K55: Target decision (stated). Quotes: “representatives of BMO then contacted Party B to determine if it would increase its offer price. Party B indicated that it would not increase its price” / “The Board determined that the G&W offer represented the superior proposal” / “Following a discussion of the terms of the merger agreement and related matters, the Board (other than Director Smith, who recused himself from the August 12, 2016 meeting) (i) determined that the merger agreement, the plan of merger” No-conflict confirmation: “BMO confirmed that it did not have any existing or contemplated material relationships with G&W in connection with the provision of any financial advisory or financing services to G&W” (P-027). | L55: =HYPERLINK("#Source text!$D$27","P-026; P-027 (main: P-026)") | M55: Q6 | O55: R053 | P55: Yes | R55: 2016-08-12 | S55: 2016-08-12 | T55: 2016-08-12 | U55: Reported day | V55: Reported | AK55: 32 | AL55: bid R052; signing R054; outcomes R055–R056 | AM55: PWRR-G&W 2016
A56: 54 | B56: 08/12/2016 | C56: PWRR, G&W and Pullman Acquisition Sub Inc. | D56: Merger agreement signed | E56: 1 | F56: 3 | H56: Executed the merger agreement (Merger Sub merges into PWRR, which survives as a wholly owned G&W subsidiary; $25.00 cash per common share; preferred converted 100-for-1 plus accrued dividends; equity awards cashed out) and, with the Eder Trusts, the voting agreement (842,742 common / 500 preferred; ~17.3% / 78.1% of record-date class shares). Company termination fee $3,785,000 (~3% of transaction value; G&W draft negotiated down from 3.85%; Party B’s draft was 3% plus expenses capped at 1%); no financing condition; outside dates 12/31/2016, or 02/28/2017 if only STB approval remains. Signing is not a bid row: agreed consideration stated here, price/formality/conditionality cells left blank. | K56: Merger agreement signed (stated). Quotes: “the Company and G&W executed the merger agreement, and the Company, G&W and the Eder Trusts executed the voting agreement” / “shall mean $3,785,000” Fee history: “termination fee equal to 3% of the transaction value in the case of G&W (which the Company had negotiated down from 3.85%)” Outside date: “if the merger is not completed by December 31, 2016 (or, if the only unsatisfied condition is STB approval of the merger, by February 28, 2017)” Financing condition: “the absence of a financing condition in the merger agreement and the representation of G&W in the merger agreement as to its financial wherewithal” Termination-fee and fiduciary-out terms were consequential for selection and are folded into this row (section 4). | L56: =HYPERLINK("#Source text!$D$29","P-028; X-023; X-010; P-025; X-022 (main: P-028)") | M56: Q8 | O56: R054 | P56: Yes | R56: 2016-08-12 | S56: 2016-08-12 | T56: 2016-08-12 | U56: Reported day | V56: Reported | AK56: 32 | AL56: Board approval R053 | AM56: PWRR-G&W 2016
A57: 55 | B57: by 08/12/2016 | C57: Party B | D57: Not selected at signing | E57: 1 | F57: 3 | G57: Strategic | H57: Still bidding when the target chose another: standing $24.00 LOI; asked to improve and declined; the target signed with G&W. Decided by: Target; Exit reason: Would not improve earlier offer. Outcome basis: Stated (the target chose another while Party B remained live). | K57: Not selected at signing (stated). Quote: “representatives of BMO then contacted Party B to determine if it would increase its offer price. Party B indicated that it would not increase its price” The target executed with G&W: “the Company and G&W executed the merger agreement” (P-028). A bidder asked to improve and declining takes Would not improve earlier offer even though the target then chose the rival and Decided by is Target (section 10.3). No late-reconfirmation row is recorded for Party B: its latest priced row (R028) is Formal and sits in a round whose finality is Inferred final, so the section 9.1 test is not met. | L57: =HYPERLINK("#Source text!$D$27","P-026; P-028 (main: P-026)") | M57: Q6 | O57: R055 | P57: Yes | Q57: 1 | S57: 2016-08-12 | T57: 2016-08-12 | U57: Relative only | V57: Assigned: bound | AH57: Target | AI57: Would not improve earlier offer | AJ57: Stated | AK57: 32 | AL57: standing bid R028; signing R054 | AM57: PWRR-G&W 2016
A58: 56 | B58: by 08/12/2016 | C58: Party E | D58: Not selected at signing | E58: 1 | F58: 3 | G58: Strategic | H58: Still live when the target chose another: standing original proposal of $21.26 per share confirmed 08/02/2016; not chosen against G&W’s $25.00. Decided by: Target; Exit reason: Lower offer than rivals. | K58: Not selected at signing (stated). Quotes: “confirmed its original proposal of $21.26 per share” / “The Board determined that the G&W offer represented the superior proposal” / “the Company and G&W executed the merger agreement” (P-028). Party E was not displaced by exclusivity (none was executed), so this is a signing outcome, not an earlier withdrawal. | L58: =HYPERLINK("#Source text!$D$22","P-021; P-027; P-028 (main: P-021)") | M58: Q4 | O58: R056 | P58: Yes | Q58: 1 | S58: 2016-08-12 | T58: 2016-08-12 | U58: Relative only | V58: Assigned: bound | AH58: Target | AI58: Lower offer than rivals | AJ58: Stated | AK58: 30 | AL58: standing bid R048 | AM58: PWRR-G&W 2016
A59: 57 | B59: 08/15/2016 | C59: PWRR (press release) | D59: Merger announced | E59: 1 | F59: post | H59: Company press release publicly announcing the transaction on Monday, 08/15/2016 before the opening of NASDAQ trading; issuer: the Company; medium: press release. No go-shop, competing post-signing proposal, agreement termination or closing is disclosed in this filing. | K59: Merger announced (stated publicity). Quote: “The Company issued a press release publicly announcing the transaction on Monday, August 15, 2016 prior to the opening of trading of” | L59: =HYPERLINK("#Source text!$D$29","P-028 (main: P-028)") | M59: Q1 | O59: R057 | P59: Yes | R59: 2016-08-15 | S59: 2016-08-15 | T59: 2016-08-15 | U59: Reported day | V59: Reported | AK59: 32 | AM59: PWRR-G&W 2016

Sheet Summary
A1: PWRR × G&W — deal ledger summary (Providence and Worcester Railroad Company / Genesee & Wyoming Inc., 2016)
A2: 1. Status and commercial account
A3: Delivery status | B3: AI first pass; not human-approved. Instruction: SEC_Deal_Ledger_Extraction_Instruction.md, revision of 19 September 2026 (short form). Supplied source: providence-worcester_2016-09-20_DEFM14A.htm — PWRR definitive proxy statement (DEFM14A) filed 09/20/2016, proxy dated 09/19/2016. Source coverage: the complete “Background of the Merger” (pp. 27–32) is reproduced in order in the Source text sheet (P-001–P-029), with every other passage used as X-001 onward.
A4: Commercial account | B4: Initiation was mixed: a Q4 2015 approach by a Class I rail partner (Party A) expressing interest in acquiring equity led, through the Board’s banker search and its 03/14/2016 decision to explore a change of control, to a broad bank-run solicitation of 29 potential buyers (11 strategic, 18 financial) in the week of 03/28/2016. Twenty-five buyers signed confidentiality agreements (no standstills); after introductory meetings and a memorandum, nine submitted non-binding IOIs received 05/19–06/01/2016 at $17.93–$26.50 per share as-converted (equity values $90–134 million), and the committee excluded the two lowest and advanced seven to management presentations and a data site. A mid-June solicitation for LOIs with agreement mark-ups (due 07/20/2016) produced six LOIs in late July at $19.20–$24.00: Party B ($24.00) and G&W ($21.15, then $22.15 including a $1.13 South Quay CVR) led; Party E ($21.26), Party D ($21.00), Party C ($19.30) and Party F ($19.20) followed; one strategic and one financial buyer elected not to submit. On 07/27/2016 the committee chose G&W and Party B for confirmatory due diligence and definitive negotiation and told the remaining bidders they were out; Party D and Party E briefly re-engaged (08/01 revised LOIs of $24.00 and $23.81, Party E supported by Party F financing), but Party D withdrew on 08/02 after the Company declined a no-sign commitment and Party E reverted to $21.26. On 08/12/2016 G&W’s final $25.00 all-cash LOI (CVR dropped, mark-ups returned, expiry 6:00 p.m. 08/13) displaced Party B’s $24.00 after Party B declined to raise, and the Board approved the merger agreement and the Eder Trusts’ voting agreement that same day. Announcement followed on 08/15/2016; no go-shop, competing post-signing proposal, agreement termination or closing is disclosed, STB approval was pending (petition 09/01/2016; voting trust submission 09/14/2016), and closing was expected in Q4 2016.
A5: 2. Deal facts
A6: Target | B6: Providence and Worcester Railroad Company (PWRR), a Rhode Island corporation; regional freight railroad in Massachusetts, Rhode Island, Connecticut and New York; NASDAQ: PWX; US public company. 4,866,593 common shares and 640 preferred shares outstanding on the 09/16/2016 record date (preferred convertible 100-for-1; non-cumulative $5.00 dividend).
A7: Focal acquirer and type | B7: Genesee & Wyoming Inc. (G&W), a Delaware corporation; NYSE: GWR; US public company; Strategic — operating short-line/regional railroad acquirer, buying through its wholly owned shell Pullman Acquisition Sub Inc. (formed 08/12/2016).
A8: Agreed consideration | B8: $25.00 per share in cash (as-converted basis: preferred deemed converted into 100 common shares plus accrued and unpaid dividends); equity awards cashed out at $25.00 (options net of exercise price; RSUs at $25.00); no financing condition; G&W representation as to financial wherewithal. All cash: Yes. No CVR in the signed terms.
A9: Signing | B9: 08/12/2016 — merger agreement among PWRR, G&W and Merger Sub; voting agreement among PWRR, G&W and the Eder Trusts (842,742 common shares, 500 preferred shares).
A10: Announcement | B10: 08/15/2016 — Company press release before the opening of NASDAQ trading.
A11: Completion | B11: Not observed in this filing (expected Q4 2016). Outside dates 12/31/2016, or 02/28/2017 if the only unsatisfied condition is STB approval. Expected closing kept separate from any observed closing.
A12: Termination fee | B12: $3,785,000 payable by the Company to G&W in specified cases (~3% of transaction value; the Company negotiated G&W’s draft down from 3.85%; Party B’s draft was 3% plus its transaction expenses capped at 1%).
A13: Filing identity and date | B13: DEFM14A definitive proxy statement for the special meeting of shareholders (10/26/2016), filed 09/20/2016; background pages 27–32. Source file: raw_filing/providence-worcester_2016-09-20_DEFM14A.htm.
A14: 3. Process and round map
A15: Processes | B15: One sale process (Process 1). No earlier attempt is disclosed (the Q4 2015 Party A approach is round 0, not a separate process); no second process, go-shop or agreement termination is disclosed. Post-signing ledger content is publicity only (R057); the STB process and the 09/06/2016 BMO conflict confirmation sit in these Summary blocks.
A16: Round 0 (pre-solicitation) | B16: R001 Party A interest (Q4 2015); R002 GHF adviser engaged (01/27/2016); R003 sale-strategy decision (03/14/2016); R004 Party A management meetings (03/22–03/23); R005 contact authorization (03/24); R006 Hinckley Allen shown acting (03/24). No Round opened row for round 0.
A17: Round 1 (week of 03/28 – 06/01/2016) | B17: R008 anchor = first outreach wave — 29 potential buyers contacted (R007); rejected candidate anchors R003 and R005. NDA wave R009–R011 (25 signers: 10 remaining strategic + 14 financial + G&W individually; no standstills). Access/differentiation: R012 (convention meetings), R013 (04/07 contact authorization), R014 (two additional Class I railroads contacted). Deadline history: R016 (05/10 set by 04/27), R017 (revised to 05/19), R018 (05/19; Enforced). Bids: R019 (nine IOIs, envelope $17.93–$26.50). Outcomes: R020 (16 residual non-submitters, inferred), R021 (06/01 decision), R022 (two low bidders dropped). Round-bidder tally: 9. Finality: Not final.
A18: Round 2 (mid-June – 07/27/2016) | B18: R023 opened the LOI stage (due 07/20/2016; mark-ups and draft documents posted to the data site 06/29–07/11). Late entrant Party C: R024 NDA, R025 IOI ($21.00), R026 catch-up access. Bids: R028–R032 (B $24.00, E $21.26, D $21.00, C $19.30, F $19.20) and R036–R037 (G&W $21.15, then $22.15). Deadline: R027 (07/20; Late bids accepted). Outcomes: R033–R034 (two non-submitters), R035 (Party A identity row), R038 (07/27 selection of G&W and Party B), R039–R042 (C, D, E, F dropped). Round-bidder tally: 6. Finality: Inferred final.
A19: Round 3 (07/27 – 08/12/2016) | B19: R043 opened confirmatory due diligence and definitive negotiation with G&W and Party B. Re-entries R044–R045; bids R046–R048; withdrawal R049; access update R050; adviser R051; final bid R052 ($25.00); Board decision R053; signing R054; signing outcomes R055–R056. Round-bidder tally: 3. Finality: Inferred final.
A20: Post-signing | B20: R057 announcement (08/15/2016); no competing proposal, go-shop activity, agreement termination or closing observed. Regulatory: STB petition for exemption filed 09/01/2016 and a voting-trust agreement submitted 09/14/2016 (X-009); outside dates X-010. Adviser conflict: on 09/06/2016 the Board considered BMO’s late disclosure of a ~5% BMO-affiliate lending participation in G&W’s secured syndicated facility and determined it was not material to BMO’s independence (P-029; X-016).
A21: 4. Participants and advisers
A22: G&W | B22: Strategic (operating short-line/regional railroad; acquires through wholly owned shell Merger Sub). First observed 04/03/2016 (NDA R011; convention meeting R012); bids R036 ($21.15 with CVR), R037 ($22.15), R052 ($25.00 cash). Winner — no exit row.
A23: Party A | B23: Strategic (Class I rail partner). First observed Q4 2015 (R001); NDA within R009; memorandum recipient; never mentioned again → Count-0 identity row R035 (Inferred: identity; possible covers R033 recommended, R020, R022). See Q4/Q5.
A24: Party B | B24: Strategic. First individual meeting 04/21/2016 (R015); LOI R028 ($24.00); prioritized for definitive negotiation 08/04/2016; declined to raise on 08/12; Not selected at signing R055 (Would not improve earlier offer).
A25: Party C | B25: Strategic late entrant. NDA R024 (early July); IOI R025 ($21.00); LOI R031 ($19.30); dropped R039 (07/27).
A26: Party D | B26: Financial (as described in the filing). LOI R030 ($21.00); dropped R040; re-entered R044; revised LOI R046 ($24.00); Withdrew R049 (terms/process; no-sign commitment declined).
A27: Party E | B27: Strategic. LOI R029 ($21.26); dropped R041; re-entered R045; revised LOI R047 ($23.81 with Party F financing); reversion R048 ($21.26); Not selected at signing R056.
A28: Party F | B28: Strategic. LOI R032 ($19.20); dropped R042 (07/27 exit); provided financing support to Party E’s withdrawn 08/01 revised proposal (recorded on R047; no re-entry row after its exit).
A29: Anonymous cohorts | B29: Two unnamed low bidders (Unknown type; dropped R022); one unnamed strategic and one unnamed financial non-submitter (R033, R034); 16 residual NDA signers closed by inference at 05/19/2016 (R020); two additional Class I railroads contacted before 04/07/2016 that never entered (R014). Cohorts are not extra parties to add to their members.
A30: Non-bidder holders | B30: The Eder Trusts (shareholders; voting agreement 08/12/2016; X-012/X-024) and GATX Corporation (4.92% common holder; Director Smith recused from process meetings because GATX might be a potential buyer; no contact, NDA or bid disclosed) are not bidders and get no outcome rows.
A31: Advisers | B31: GHF (Greene Holcomb & Fisher LLC) → BMO Capital Markets Corp. — Company financial adviser; engaged 01/27/2016 (R002); GHF’s business acquired by BMO 08/01/2016 (same relationship); aggregate fee ~$2.52 million (X-015); BMO-affiliate lending participation in G&W’s 2015 facility disclosed late and considered not material by the Board on 09/06/2016 (P-029; X-016). Hinckley, Allen & Snyder LLP — Company legal counsel (R006; first shown acting 03/24/2016). Simpson Thacher & Bartlett LLP — G&W legal counsel (R051; first shown acting 08/10/2016). The Company’s STB counsel is unnamed (P-026) and gets no adviser row. Disclosed attributes: PWRR and G&W are US public companies (NASDAQ: PWX; NYSE: GWR); ownership and country of the anonymous parties are not disclosed.
A32: 5. Counts and auction screen
A33: Auction screen | B33: MET — more than one independent prospective acquiring bidder unit executed bidder-target confidentiality agreements for this process (25 in the week-of-03/28 wave plus Party C; G&W among them). No lender-only, adviser or rollover-holder agreements are included; the Eder Trusts’ voting agreement is not a bidder NDA. Extraction proceeds regardless of the screen.
A34: Contacts (ledger tally) | B34: =SUMIFS('Deal ledger'!$Q$3:$Q$100,'Deal ledger'!$D$3:$D$100,"Contact",'Deal ledger'!$P$3:$P$100,"Yes")+SUMIFS('Deal ledger'!$Q$3:$Q$100,'Deal ledger'!$D$3:$D$100,"Bidder interest",'Deal ledger'!$P$3:$P$100,"Yes")
A35: → composition and filing assertions | B35: 31 from Contact rows (29 in the GHF outreach wave + 2 additional Class I railroads approached by the Company) plus 1 from the Party A Bidder interest row, which carries the Q4 2015 first contact = 32 contact units. Party A’s 03/22–03/23 meeting and Party B’s 04/21 meeting are Count 0 repeats. Filing: GHF contacted 11 potential strategic buyers and 18 potential financial buyers (29) in the week of 03/28/2016; the Company also approached two additional Class I railroads (P-004; P-006).
A36: NDA signers (ledger tally) | B36: =SUMIFS('Deal ledger'!$Q$3:$Q$100,'Deal ledger'!$D$3:$D$100,"NDA signed",'Deal ledger'!$P$3:$P$100,"Yes")
A37: → filing assertions and reconciliation | B37: Background: each of the 11 potential strategic buyers and 14 potential financial buyers executed confidentiality agreements (25), plus Party C’s early-July agreement = 26 signatures on the ledger’s reading; the Board’s reasons state “25 of whom entered into confidentiality agreements” (X-002). Q3 reconciles: the reasons’ 25 may exclude Party C or one strategic signer.
A38: IOI submitters | B38: 9 (stated; R019 cohort, envelope $17.93–$26.50; filing: “nine written indications of interest”, P-008).
A39: LOI submitters | B39: 6 (stated; B, G&W, E, D, C, F — R028–R032, R036; plus G&W’s 07/26 revision R037. Filing: “six LOIs”, P-012; group envelope $19.20–$24.00 / $96–121 million).
A40: Round-bidder tallies (R1 / R2 / R3) | B40: =SUMIFS('Deal ledger'!$Q$3:$Q$100,'Deal ledger'!$D$3:$D$100,"Bid",'Deal ledger'!$F$3:$F$100,"1",'Deal ledger'!$P$3:$P$100,"Yes")&" / "&SUMIFS('Deal ledger'!$Q$3:$Q$100,'Deal ledger'!$D$3:$D$100,"Bid",'Deal ledger'!$F$3:$F$100,"2",'Deal ledger'!$P$3:$P$100,"Yes")&" / "&SUMIFS('Deal ledger'!$Q$3:$Q$100,'Deal ledger'!$D$3:$D$100,"Bid",'Deal ledger'!$F$3:$F$100,"3",'Deal ledger'!$P$3:$P$100,"Yes")
A41: → scope | B41: Bidder units newly represented as submitting in each round; not submissions and not unique bidders across the deal. R2 counts Party C’s IOI (R025) plus five LOIs; R3 counts D, E and G&W; later bids by the same bidder in the same round add 0 (G&W R037, C R031, E R048).
A42: Exit units and inferred share | B42: =SUMIFS('Deal ledger'!$Q$3:$Q$100,'Deal ledger'!$AI$3:$AI$100,"<>",'Deal ledger'!$P$3:$P$100,"Yes")&" exit units; "&SUMIFS('Deal ledger'!$Q$3:$Q$100,'Deal ledger'!$AJ$3:$AJ$100,"Inferred: residual",'Deal ledger'!$P$3:$P$100,"Yes")&"/"&SUMIFS('Deal ledger'!$Q$3:$Q$100,'Deal ledger'!$AI$3:$AI$100,"<>",'Deal ledger'!$P$3:$P$100,"Yes")&" inferred by residual"
A43: → per-stage balance (Process 1) | B43: R0/R1: 25 entrants − 16 inferred non-submitters (R020) − 2 low bidders (R022) = 7 continuing. R2: +1 (Party C, R024) − 2 non-submitters (R033–R034) − 4 dropped (R039–R042) = 2 continuing. R3: +2 re-entries (R044–R045) − 1 withdrawal (R049) − 2 signing outcomes (R055–R056) = 1 (winner). Total: 26 entrants + 2 re-entries − 27 exit units = 1. Party A’s Count-0 identity row (R035) moves no counts.
A44: → balance formula | B44: =SUMIFS('Deal ledger'!$Q$3:$Q$100,'Deal ledger'!$D$3:$D$100,"NDA signed",'Deal ledger'!$P$3:$P$100,"Yes")+SUMIFS('Deal ledger'!$Q$3:$Q$100,'Deal ledger'!$D$3:$D$100,"Re-entered",'Deal ledger'!$P$3:$P$100,"Yes")-SUMIFS('Deal ledger'!$Q$3:$Q$100,'Deal ledger'!$AI$3:$AI$100,"<>",'Deal ledger'!$P$3:$P$100,"Yes")
A45: 6. Comparability and inputs
A46: Per-share basis | B46: All offer prices are as-converted (preferred 100-for-1); the filing gives no decomposed per-share values except G&W’s cash/CVR split. All amounts are US dollars; no currency conversion attempted.
A47: Market benchmarks | B47: Closing price 08/12/2016 (last trading day before announcement): $16.30 — the $25.00 consideration is stated as a 53% premium (X-003). Closing price 09/16/2016: $24.88 (X-004). 2016 Q3 trading range through 09/16/2016: $15.60–$25.00 (X-005).
A48: Share counts and optional calculation | B48: 4,866,593 common + 640 preferred (as-converted 64,000) = 4,930,593 as-converted shares on the 09/16/2016 record date; 53,368 options (18,368 vested) and 43,500 RSUs held by directors/officers (X-005; X-006). Optional labelled calculation (not filing-stated; excludes options/RSUs): $25.00 × 4,930,593 = $123.26 million implied equity value.
A49: Contingent consideration | B49: G&W’s July bids included a $1.13 per-share CVR tied to the subsequent sale of the South Quay property (book value $12.5 million used in BMO’s analyses); a contingent cash payment, so those bids remain All cash = Yes. The signed $25.00 terms exclude it.
A50: Other-scope proposals | B50: None disclosed: every indication, LOI and final bid is for 100% of the outstanding common stock on an as-converted basis (P-009; P-016). No segment, asset or minority-stake proposals, so no Other-scope rows.
A51: Valuation statements (not bids) | B51: BMO’s implied per-share reference ranges: selected companies $10.95–$14.56 and $11.42–$15.09; precedent transactions $10.54–$26.50; DCF $10.82–$12.34 — each compared with the $25.00 consideration (X-017–X-019). These are adviser analyses, not offers, and are not entered in bid-price cells.
A52: Glossary | B52: NDA = confidentiality agreement; IOI = indication of interest (non-binding); LOI = letter of intent (non-binding); CVR = contingent value right (extra cash tied to the South Quay property sale); confirmatory diligence = final-stage diligence after selection; data site = internet data room; exclusivity = a target commitment to deal only with one bidder (requested by several bidders; never granted); go-shop = post-signing solicitation period (none); STB = Surface Transportation Board; as-converted = treating preferred as converted 100-for-1 into common. Layout-only HTML decoding and whitespace normalization were applied to the filing text in the Source text sheet.
A53: Unverifiable items | B53: Closing is not observed in this filing; the confidentiality-agreement count (25 vs 26) is reconciled in Q3; Party A’s later path is unresolved (Q5); no post-signing competition is disclosed.

Sheet Questions
A1: Q | B1: Review topic | C1: Recommended answer | D1: Why and source | E1: Affected rows/fields | F1: Consequence of changing it | G1: Status | H1: Reviewer note
A2: Q1 | B2: Process and round map, boundaries and finality | C2: Keep one process and three rounds: R1 anchored on the week-of-03/28/2016 first outreach wave (R008), R2 opened mid-June 2016 by the LOI instruction (R023), R3 opened 07/27/2016 by selection and the move to definitive negotiation (R043). Round 0 keeps the pre-solicitation items with no Round opened row. Finality: R1 Not final; R2 and R3 Inferred final. Keep the 04/03–04/06 convention meetings as one Information access changed row (R012) and Party C’s catch-up access as one row (R026); keep the 08/09–08/11 G&W continued-diligence grant as a Material process update (R050). Post-signing: publicity only (R057). | D2: The executed outreach is the preferred R1 anchor (P-004); rejected candidates R003 and R005 are retained as their own rows so the boundary can be moved. R2 alternative boundary 06/01/2016 (R021) rejected because no updated offers were sought then (P-008–P-009). R3 alternative boundaries 08/04 and 08/12 rejected because definitive negotiation with the selected bidders began on 07/27/2016 (P-020). R2 is Inferred final because the target moved to confirmatory due diligence and definitive negotiation at its close; R3 because it concluded with the executed agreement. Access rows follow section 4 (P-005; P-011); the 08/09 continued-diligence grant preceded G&W’s final bid (P-023). | E2: R003, R005, R007, R008, R012, R021, R023, R026, R038, R043, R050, R057; Round, Round finality, What happened | F2: Moving any boundary changes the round-bidder tallies (9/6/3) and the round map; reclassifying the access rows changes the access narrative but no counts. | G2: Pending
A3: Q2 | B3: Deadline history and treatments | C3: Record three versions: 05/10/2016 set by the 04/27/2016 board report (R016; superseded before arrival, no milestone row); revised to 05/19/2016 (R017; Extended) for the stated reason; 05/19/2016 reached while operative and treated Enforced (R018). The 07/20/2016 LOI due date (R023; R027) is treated Late bids accepted because G&W’s 07/21/2016 LOI and the other late-July LOIs were considered without a revision. G&W’s 6:00 p.m. 08/13/2016 offer expiry is not a bid deadline and stays in Terms (R052). | D3: Section 8.3 rules. The IOI receipt window 05/19–06/01 straddles the due date, so no submission is late and Enforced (not Late bids accepted) applies (P-008). The revision reason is stated (P-007). The mid-June LOI instruction carries its due date on the R2 opening row, with the milestone row at 07/20/2016 (P-009; P-012; P-014). | E3: R016, R017, R018, R023 (Due date), R027, R052 (offer expiry in Terms); Deadline treatment, Due date, Date from/Date to of R017 | F3: Changing treatments alters the Summary deadline map and the R2 narrative; treating the May IOIs as late would contradict the filing’s receipt window. | G3: Pending
A4: Q3 | B4: Confidentiality-agreement counts and auction screen | C4: Working total: 26 executed confidentiality agreements — the 25 of the week-of-03/28 wave (11 strategic + 14 financial) plus Party C’s early-July agreement (R009–R011, R024). Read the Board’s reasons’ “25 of whom entered into confidentiality agreements” (X-002) as the reasons’ summary figure, most likely omitting Party C; alternatively the wave could have produced 24 signatures (10 strategic + 14 financial) with the total reaching 25 including Party C. Auction screen: met either way. | D4: Background supplies both specific statements: “Each of the potential strategic buyers and 14 potential financial buyers subsequently executed confidentiality agreements” and Party C’s separate agreement after its early-July approach (P-004; P-011). The reasons cite 25 (X-002). Section 3.2 prefers the specific background passages; the conflict is preserved here rather than silently resolved. | E4: R009, R010, R011, R024; Count cells; Summary “NDA signers” and auction screen | F4: If the total is 25 including Party C, R009 drops to 9 strategic signers and, if the submitter base stays 9, the inferred residual (R020) becomes 15 and the inferred share changes. | G4: Pending
A5: Q4 | B5: Inferred closures and per-stage balance | C5: Keep two inferred rows: R020 (Did not submit, Inferred: residual — 25 signers − 9 IOI submitters = 16, at the 05/19/2016 deadline) and R035 (Party A, Count 0, Inferred: identity, at 07/20/2016). All other outcomes are stated: two low bidders dropped 06/01 (R022), two LOI non-submitters (R033–R034), four 07/27 drops (R039–R042), one withdrawal (R049), two signing outcomes (R055–R056). Balance: R1 7 continuing; R2 2; R3 1 (winner); 16 of 27 exit units inferred. | D5: Section 10.2 arithmetic; base from P-004 (25 signers) and P-008 (9 submitters). The base is a stated exact number, so no bounds are needed; if the Q3 count changes, the residual changes by the same amount (flagged). R035 records only that Party A was out by the first named continuing set (P-012; P-020). | E5: R020, R022, R033, R034, R035, R039–R042, R049, R055, R056; Count, Outcome basis, Decided by, Exit reason | F5: Reclassifying any stated exit as inferred (or vice versa) changes the inferred-share arithmetic and balance; moving R035 to 05/19/2016 shifts its transition but no counts. | G5: Pending
A6: Q5 | B6: Identity mappings, anonymous cohorts and non-participants | C6: Recommended identities: the nine IOI submitters are Party B, G&W, Party D, Party E, Party F, the two unnamed low bidders and the two unnamed LOI non-submitters (one strategic, one financial). Party A is most likely the unnamed strategic LOI non-submitter (R033) and is placed at 07/20/2016 with Count 0; alternatives are the 16 residual non-submitters (R020, which would move it to 05/19) or a low bidder (R022). Party B’s 04/21 meeting and Party A’s 03/22–03/23 meetings are repeats within the 29-buyer wave (Count 0). GATX’s possible-buyer recusal is not a participation event; the two additional Class I railroads never entered. | D6: Identifications follow the stage arithmetic (seven advancing = nine minus two low bidders; five of the seven plus Party C submitted LOIs) and the named LOI list (P-008; P-012; P-020). Party A’s last appearance is the memorandum recipient list (P-007). GATX recusal: P-020. Class I contacts: P-006. | E6: R014, R015, R019, R022, R033, R034, R035; Who, Count, Related rows; Summary participant list | F6: Re-identifying Party A (e.g., as a low bidder) would move its Count-0 row to R022 and change the reading of the two anonymous cohorts; no counts are asserted on this basis either way. | G6: Pending
A7: Q6 | B7: Formality, conditions and late-reconfirmation calls | C7: Formality: Formal for Party B (R028), G&W (R036–R037, R052) and Party D (R030, carried to R046) on returned agreement/voting-agreement mark-ups; Informal for the nine-IOI cohort (R019), Party C (R025, R031), Party E (R029, R047, R048) and Party F (R032) — Party E’s issues summary is the borderline call (section 9.2 working default), flagged. Conditions: Heavy for the nine IOIs (pre-substantive-diligence context), C, D, E, F and G&W’s July LOIs (stated multi-week or exclusive diligence periods); Light for Party B (expedited review) and G&W’s 08/12 final bid (diligence completed; final documentation only; financing silent). No Bid reaffirmed row is recorded: Party B’s latest priced row is Formal and sits in an Inferred-final round, so the section 9.1 test fails; its 08/04 revised draft gets no row (further draft in the definitive stage). | D7: Formality signals/default: P-013/P-016/P-014 mark-ups and P-015 (issues summary) via P-012. Conditions tests: P-008, P-014–P-018, P-021, P-024. Late-reconfirmation conditions (a)–(c) with failure of (b): P-023; P-028. | E7: R019, R025–R032, R036–R037, R046–R048, R052, R055 (Formality, Conditions level, Conditions detail, Terms or outcome) | F7: Downgrading Party B or G&W to Informal changes the documentation profile but not prices or counts; upgrading Party E to Formal would make it a formal LOI, without changing selection. | G7: Pending
A8: Q7 | B8: Assigned Working dates that decide order | C8: Conventions used (all disclosed in Date method): R009–R010 03/28/2016 (signing-wave first day, Assigned: bound); R017 05/08/2016 (midpoint of the 04/27–05/19 revision window); R019 05/19/2016 and R028–R032 07/20/2016 (solicitation due dates, Assigned: deadline); R039–R042 07/27/2016 (notifications after the decision, Assigned: decision day); R044–R045 07/29/2016. Within 08/12/2016 the order is G&W bid (morning) → Board decision (afternoon) → signing → signing outcomes, per the stated sequence; the announcement follows on 08/15. R008 shares 03/28/2016 with R007/R009–R010 as a display tie. | D8: Section 8.1 rules 2–6 and the order constraint; the May IOIs example (due date inside the receipt window) applies at R019. Same-day sequencing follows the filing’s own order (P-024; P-025; P-026; P-028). | E8: Date from, Date to, Working date, Date basis, Date method of R008–R010, R017, R019, R028–R032, R039–R042, R044–R045, R052–R056 | F8: Changing an assigned date reorders rows (sorting is by Working date with # breaking ties) but not facts. | G8: Pending
A9: Q8 | B9: Comparability, consideration form and normalization | C9: Keep all per-share figures on the as-converted basis the filing used (P-008; P-009) and label the optional $123.26 million equity-value calculation as non-filing arithmetic. Classify G&W’s July cash-plus-CVR bids as All cash = Yes (contingent cash, not securities) with the $1.13 South Quay CVR and payoff trigger in Terms. Record no Other-scope bids (all proposals were for 100% of the common on an as-converted basis). Keep BMO’s implied reference ranges in Summary only, as valuation statements, never in bid-price cells. | D9: Consideration rules (section 9.4): P-014 for the CVR split and South Quay basis; P-005; P-009; P-012 for the as-converted basis; X-017–X-019 for the BMO ranges; X-005/X-006 for share counts. The $12.5 million South Quay book value is BMO’s input (financial analysis pages 38–39). | E9: R019, R025–R032, R036–R037, R052, R054; Price kind/origin, Currency, All cash, Cash at closing; Summary comparability block | F9: Treating the CVR as non-cash would change All cash to No for the July G&W bids; entering BMO’s ranges as prices would create false observations — both explicitly rejected above. | G9: Pending

Sheet Source text
A1: Paragraph | B1: Section | C1: Page | D1: Text
A2: P-001 | B2: Proposal No. 1—The Merger — Background of the Merger | C2: 27 | D2: In the fourth quarter of 2015, Robert H. Eder (the Company’s Chairman and Chief Executive Officer) and Frank K. Rogers (the Company’s Vice President and Chief Commercial Officer) met with one of the Company’s Class I rail partners (“Party A”) to discuss joint commercial opportunities. During the meeting, Party A suggested possible joint venture arrangements and expressed some interest in acquiring equity in the Company to further develop strategic opportunities and enhance regional connectivity. Upon receiving a report of this meeting, in recognition of its public company obligations, the Board appointed a subcommittee of two independent directors, Frank W. Barrett and Richard W. Anderson, to interview potential investment bankers to represent the Company in possible negotiations with Party A and to assist the Board in evaluating additional strategic options for the realization of shareholder value, including potential change in control transactions. The subcommittee interviewed several investment banking firms, including Greene Holcomb & Fisher LLC (the business of which was subsequently acquired by BMO Capital Markets Corp. and which we refer to as “GHF” prior to such acquisition and “BMO” thereafter). During the executive session of the Board’s regular quarterly meeting held on January 27, 2016 (which Director Alfred P. Smith did not attend), the subcommittee recommended to the Board that the Company retain GHF as its investment banking firm. At that meeting, representatives of GHF discussed with the Board its qualifications and a proposed process should the directors ultimately decide to proceed with a change in control transaction. As part of the interview process, GHF represented to the Company that it would not represent any potential buyer of the Company in connection with an offer to purchase the Company or any person proposing to provide financing in connection with such an offer. Following this presentation, the Board approved the subcommittee’s recommendation and the Company engaged GHF. In selecting GHF, the Board considered, among other things, the fact that GHF was a reputable investment banking firm with substantial experience advising companies in the rail sector and in providing strategic advisory services in general, GHF had recent experience providing strategic advisory services in connection with the sale of a short-line railroad and, in the Board’s opinion, GHF would commit appropriate attention, resources and personnel to the process.
A3: P-002 | B3: Proposal No. 1—The Merger — Background of the Merger | C3: 27 | D3: At a special meeting of the Board held on March 14, 2016, representatives of GHF discussed their evaluation of the Company’s business operations and strategy for improving operational and financial performance, as well as railroad industry dynamics more generally and their impact on current railroad valuations. Representatives of GHF then proposed a process pursuant to which the Company would proceed with discussions with Party A and also solicit interest from other potential third parties regarding a change in control transaction. The Board considered various factors, including the marketplace, the risks attendant to engaging in the process discussed with representatives of GHF, the Company’s overall strategic position, and the challenges attendant to improving the Company’s financial performance in order to maximize shareholder value and concluded, based upon its examination of these and other factors, that it was in the best interest of the Company 27 Table of Contents and its shareholders to proceed with the transaction strategy discussed with representatives of GHF. In light of the potentially significant time and effort involved in pursuing such exploratory transaction strategy, as well as the possible need to provide guidance to GHF and management on short notice, at the conclusion of the meeting, the Board appointed a special committee of independent directors of the Board (which we refer to as the “Transaction Committee”), composed of Frank W. Barrett (Chair), Richard W. Anderson and James C. Garvey, for the purpose of assisting in the supervision and oversight of the process on the full Board’s behalf and making a recommendation to the full Board. The Transaction Committee did not have the authority to approve or enter into a change of control transaction, which, under Rhode Island law, is an authority that can only be exercised by the full Board. At the time of appointment, Messrs. Barrett and Garvey had been elected by the preferred shareholders and Mr. Anderson had been elected by the common shareholders at the 2015 annual shareholders meeting. At the Company’s 2016 annual shareholders meeting on April 27, 2016, Messrs. Barrett and Anderson were re-elected as directors by the common shareholders and Mr. Garvey was re-elected as a director by the preferred shareholders.
A4: P-003 | B4: Proposal No. 1—The Merger — Background of the Merger | C4: 28 | D4: On March 22, 2016 and March 23, 2016, Daniel T. Noreck (the Company’s Chief Financial Officer and Treasurer) and other members of the senior management team of the Company met with various representatives of Party A.
A5: P-004 | B5: Proposal No. 1—The Merger — Background of the Merger | C5: 28 | D5: On March 24, 2016, the Transaction Committee met by telephone conference to discuss the results of management’s meeting with Party A and to discuss next steps in the process. Members of management and representatives of each of GHF and the Company’s legal counsel, Hinckley, Allen & Snyder LLP (which we refer to as “Hinckley Allen”), participated in all meetings of the Transaction Committee, except as otherwise indicated. At this meeting, Mr. Noreck reported that he and other members of the senior management team had met with various representatives of Party A on March 22 and 23, 2016 and had informed Party A of GHF’s engagement. The Transaction Committee authorized GHF to contact Party A as well as other potential buyers to determine their level of interest in a change in control transaction. During the week of March 28, 2016, in accordance with the Transaction Committee’s directives, representatives of GHF contacted 11 potential strategic buyers (including Party A) and 18 potential financial buyers. Each of the potential strategic buyers and 14 potential financial buyers subsequently executed confidentiality agreements. The confidentiality agreements did not contain any “standstill” or similar provision that would prohibit a potential buyer from submitting a proposal or making an offer to acquire the Company.
A6: P-005 | B6: Proposal No. 1—The Merger — Background of the Merger | C6: 28 | D6: Between April 3, 2016 and April 6, 2016, representatives of GHF and members of the Company’s management held a series of introductory meetings with five potential strategic buyers (including G&W) at the American Short Line and Regional Railroad Association’s 2016 Connections Convention (“2016 Connections Convention”).
A7: P-006 | B7: Proposal No. 1—The Merger — Background of the Merger | C7: 28 | D7: On April 7, 2016, the Transaction Committee met by telephone conference and discussed the process to date with representatives of GHF. Representatives of GHF reported that they and Company management had held a series of introductory meetings with five potential strategic buyers (including G&W) at the 2016 Connections Convention. Mr. Noreck reported that the Company had also approached two additional Class I railroads to determine their interest in a possible transaction. After discussion, the Transaction Committee authorized representatives of GHF, on behalf of the Company, to contact each of the five interested parties with whom management had met at the 2016 Connections Convention, as well as other potential strategic buyers (including certain Class I railroads) and private equity firms who had entered into confidentiality agreements with the Company to confirm their continuing interest. Subsequently, on April 21, 2016, the Company and representatives of GHF held an introductory meeting with another potential strategic buyer (“Party B”).
A8: P-007 | B8: Proposal No. 1—The Merger — Background of the Merger | C8: 28 | D8: With the assistance of GHF, the Company prepared a memorandum concerning the Company and its prospects, which was distributed to the potential buyers, including Party A, Party B and G&W, that had executed confidentiality agreements. The Transaction Committee met with representatives of GHF by telephone conference on April 22, 2016 and discussed the status of discussions with potential buyers. On April 27, 2016, 28 Table of Contents the Board met in executive session (without Mr. Eder present) with representatives of GHF and discussed the status of the process, including that each potential buyer had been advised to submit a non-binding indication of interest by May 10, 2016 (which deadline was subsequently postponed to May 19, 2016 to ensure the potential buyers had sufficient time to formulate their most compelling offers).
A9: P-008 | B9: Proposal No. 1—The Merger — Background of the Merger | C9: 29 | D9: Between May 19, 2016 and June 1, 2016, the Company received nine written indications of interest (“IOIs”) from potential buyers, with offer prices per share ranging from $17.93 to $26.50 (assuming the conversion of preferred stock into common stock), implying equity values of $90 million to $134 million. The Transaction Committee met by telephone conference on May 23, 2016 and again on June 1, 2016 to consider the IOIs. In view of the substantial amount of management time that would be required for management presentations, the Transaction Committee concluded that the two low bidders should be excluded from that process. The Transaction Committee authorized representatives of GHF to schedule in-person management presentations with the remaining seven potential buyers and allow these parties to conduct additional due diligence. These potential buyers were given access to an internet data site to conduct legal and financial due diligence.
A10: P-009 | B10: Proposal No. 1—The Merger — Background of the Merger | C10: 29 | D10: In mid-June 2016, at the direction of the Transaction Committee, representatives of GHF instructed all potential buyers to submit non-binding letters of intent (“LOIs”) by July 20, 2016, together with mark-ups of the forms of merger agreement, disclosure letter and voting agreement, which GHF indicated would be posted to the internet data site. Potential buyers were instructed to provide a valuation for the Company based on the purchase of 100% of the outstanding common stock on a dollar per share basis (assuming conversion of the preferred stock into common stock) or the financial terms of any non-cash proposal.
A11: P-010 | B11: Proposal No. 1—The Merger — Background of the Merger | C11: 29 | D11: On June 29, 2016, the Company posted an initial draft of merger agreement to the internet data site, and on June 30, 2016, the Company posted an initial draft of voting agreement with respect to the common stock and preferred stock held by the Eder Trusts. On July 11, 2016, the Company posted an initial draft of disclosure letter to the internet data site.
A12: P-011 | B12: Proposal No. 1—The Merger — Background of the Merger | C12: 29 | D12: Over the course of June and July 2016, each of the potential buyers and their respective advisors engaged in due diligence of the Company’s business and financial condition, including holding meetings with certain members of the Company’s management team. The Transaction Committee met on June 30, 2016 to receive a status update on the management presentations and due diligence efforts of the potential buyers. In early July 2016, a potential strategic buyer that had not previously been part of the process (“Party C”) approached the Company’s management and expressed interest in acquiring the Company. After executing a confidentiality agreement, Party C was provided the memorandum concerning the Company provided to the other potential buyers. On July 12, 2016, Party C submitted an IOI with an offer price per share of $21.00 (implying an equity value of $108 million). Subsequently, Party C was provided access to the internet data site and the Company’s management held a management presentation with Party C by telephone on July 14, 2016.
... A54: X-024 | B54: Summary — Voting Agreement | C54: 4 | D54: Voting Agreement (page 26) The Robert H. Eder Trust and the Linda Eder Trust, which we refer to as the “Eder Trusts,” have executed a voting agreement with G&W and the Company under which the Eder Trusts have agreed to vote their shares in favor of approving the merger agreement. As of the record date, the Eder Trusts held 842,742 shares of common stock, representing approximately 17.3% of the outstanding shares of common stock, and 500 shares of preferred stock, representing approximately 78.1% of the outstanding shares of preferred stock.

Sheet Lists
A1: What happened | B1: Type | C1: Formality | D1: Conditions level | E1: Include | F1: Date basis | G1: Date method | H1: Price kind | I1: Price origin | J1: All cash | K1: Deadline treatment | L1: Round finality | M1: Decided by | N1: Exit reason | O1: Outcome basis
A2: Target interest | B2: Strategic | C2: Formal | D2: None | E2: Yes | F2: Reported day | G2: Reported | H2: Point | I2: Stated | J2: Yes | K2: Extended | L2: Announced as final | M2: Bidder | N2: Value below market price | O2: Stated
A3: Bidder interest | B3: Financial | C3: Informal | D3: Light | E3: No | F3: Inferred day | G3: Inferred | H3: Bidder range | I3: Carried forward | J3: No | K3: Extended; Late bids accepted | L3: Inferred final | M3: Target | N3: Value at or below market price | O3: Inferred: residual
A4: Target sale decision | B4: Mixed | C4: Insufficient evidence | D4: Heavy | F4: Reported interval | G4: Assigned: deadline | H4: Group envelope | I4: Inferred | J4: Not stated | K4: Late bids accepted | L4: Not final | M4: Both | N4: Value below earlier offer | O4: Inferred: exclusivity
A5: Activist pressure | B5: Unknown | C5: Varies | D5: Insufficient evidence | F5: Approximate window | G5: Assigned: decision day | H5: Bound only | K5: Enforced | M5: Unknown | N5: Value at earlier offer | O5: Inferred: silent
A6: Activist involvement | D6: Varies | F6: Relative only | G6: Assigned: midpoint | H6: Undisclosed | K6: Passed without action | N6: Would not improve earlier offer | O6: Inferred: identity
A7: Adviser engaged | F7: Undated | G7: Assigned: bound | K7: Unclear | N7: Lower offer than rivals
A8: Adviser service observed | G8: Assigned: sequence | K8: No deadline stated | N8: Terms or process
A9: Adviser ended | N9: Other stated reason
A10: Contact | N10: Not stated
A11: NDA signed
A12: Round opened
A13: Deadline set
A14: Deadline revised
A15: Deadline
A16: Target decision
A17: Information access changed
A18: Material process update
A19: Exclusivity changed
A20: Bid
A21: Bid reaffirmed
A22: Offer update
... A41: Closed
